{
  "ticker": "NVDA",
  "endpoint": "cash-flow-statement",
  "fetched_at": "2025-09-05T14:21:18.709500",
  "data": [
    {
      "date": "2025-07-27",
      "symbol": "NVDA",
      "reportedCurrency": "USD",
      "cik": "0001045810",
      "fillingDate": "2025-08-27",
      "acceptedDate": "2025-08-27 16:52:07",
      "calendarYear": "2026",
      "period": "Q2",
      "netIncome": 26422000000,
      "depreciationAndAmortization": 669000000,
      "deferredIncomeTax": 17000000,
      "stockBasedCompensation": 1625000000,
      "changeInWorkingCapital": -11022000000,
      "accountsReceivables": -5676000000,
      "inventory": -3622000000,
      "accountsPayables": 1314000000,
      "otherWorkingCapital": -3038000000,
      "otherNonCashItems": -2346000000,
      "netCashProvidedByOperatingActivities": 15365000000,
      "investmentsInPropertyPlantAndEquipment": -1895000000,
      "acquisitionsNet": -294000000,
      "purchasesOfInvestments": -8158000000,
      "salesMaturitiesOfInvestments": 3220000000,
      "otherInvestingActivites": 0,
      "netCashUsedForInvestingActivites": -7127000000,
      "debtRepayment": 0,
      "commonStockIssued": 0,
      "commonStockRepurchased": -9720000000,
      "dividendsPaid": -244000000,
      "otherFinancingActivites": -1869000000,
      "netCashUsedProvidedByFinancingActivities": -11833000000,
      "effectOfForexChangesOnCash": 0,
      "netChangeInCash": -3595000000,
      "cashAtEndOfPeriod": 11639000000,
      "cashAtBeginningOfPeriod": 15234000000,
      "operatingCashFlow": 15365000000,
      "capitalExpenditure": -1895000000,
      "freeCashFlow": 13470000000,
      "link": "https://www.sec.gov/Archives/edgar/data/1045810/000104581025000209/0001045810-25-000209-index.htm",
      "finalLink": "https://www.sec.gov/Archives/edgar/data/1045810/000104581025000209/nvda-20250727.htm"
    },
    {
      "date": "2025-04-27",
      "symbol": "NVDA",
      "reportedCurrency": "USD",
      "cik": "0001045810",
      "fillingDate": "2025-05-28",
      "acceptedDate": "2025-05-28 16:32:57",
      "calendarYear": "2026",
      "period": "Q1",
      "netIncome": 18775000000,
      "depreciationAndAmortization": 611000000,
      "deferredIncomeTax": -2177000000,
      "stockBasedCompensation": 1474000000,
      "changeInWorkingCapital": 8654000000,
      "accountsReceivables": 933000000,
      "inventory": -1258000000,
      "accountsPayables": 941000000,
      "otherWorkingCapital": 8038000000,
      "otherNonCashItems": 77000000,
      "netCashProvidedByOperatingActivities": 27414000000,
      "investmentsInPropertyPlantAndEquipment": -1227000000,
      "acquisitionsNet": -383000000,
      "purchasesOfInvestments": -7195000000,
      "salesMaturitiesOfInvestments": 3589000000,
      "otherInvestingActivites": 0,
      "netCashUsedForInvestingActivites": -5216000000,
      "debtRepayment": 0,
      "commonStockIssued": 0,
      "commonStockRepurchased": -14095000000,
      "dividendsPaid": -244000000,
      "otherFinancingActivites": -1214000000,
      "netCashUsedProvidedByFinancingActivities": -15553000000,
      "effectOfForexChangesOnCash": 0,
      "netChangeInCash": 6645000000,
      "cashAtEndOfPeriod": 15234000000,
      "cashAtBeginningOfPeriod": 8589000000,
      "operatingCashFlow": 27414000000,
      "capitalExpenditure": -1227000000,
      "freeCashFlow": 26187000000,
      "link": "https://www.sec.gov/Archives/edgar/data/1045810/000104581025000116/0001045810-25-000116-index.htm",
      "finalLink": "https://www.sec.gov/Archives/edgar/data/1045810/000104581025000116/nvda-20250427.htm"
    },
    {
      "date": "2025-01-26",
      "symbol": "NVDA",
      "reportedCurrency": "USD",
      "cik": "0001045810",
      "fillingDate": "2025-02-26",
      "acceptedDate": "2025-02-26 16:48:33",
      "calendarYear": "2025",
      "period": "Q4",
      "netIncome": 22091000000,
      "depreciationAndAmortization": 543000000,
      "deferredIncomeTax": -598000000,
      "stockBasedCompensation": 1321000000,
      "changeInWorkingCapital": -5863000000,
      "accountsReceivables": -5369000000,
      "inventory": -2424000000,
      "accountsPayables": 867000000,
      "otherWorkingCapital": 1063000000,
      "otherNonCashItems": -865000000,
      "netCashProvidedByOperatingActivities": 16629000000,
      "investmentsInPropertyPlantAndEquipment": -1077000000,
      "acquisitionsNet": -542000000,
      "purchasesOfInvestments": -7488000000,
      "salesMaturitiesOfInvestments": 1887000000,
      "otherInvestingActivites": 22000000,
      "netCashUsedForInvestingActivites": -7198000000,
      "debtRepayment": 0,
      "commonStockIssued": 0,
      "commonStockRepurchased": -7811000000,
      "dividendsPaid": -245000000,
      "otherFinancingActivites": -1893000000,
      "netCashUsedProvidedByFinancingActivities": -9949000000,
      "effectOfForexChangesOnCash": 0,
      "netChangeInCash": -518000000,
      "cashAtEndOfPeriod": 8589000000,
      "cashAtBeginningOfPeriod": 9107000000,
      "operatingCashFlow": 16629000000,
      "capitalExpenditure": -1077000000,
      "freeCashFlow": 15552000000,
      "link": "https://www.sec.gov/Archives/edgar/data/1045810/000104581025000023/0001045810-25-000023-index.htm",
      "finalLink": "https://www.sec.gov/Archives/edgar/data/1045810/000104581025000023/nvda-20250126.htm"
    },
    {
      "date": "2024-10-27",
      "symbol": "NVDA",
      "reportedCurrency": "USD",
      "cik": "0001045810",
      "fillingDate": "2024-11-20",
      "acceptedDate": "2024-11-20 16:31:22",
      "calendarYear": "2025",
      "period": "Q3",
      "netIncome": 19309000000,
      "depreciationAndAmortization": 478000000,
      "deferredIncomeTax": -603000000,
      "stockBasedCompensation": 1252000000,
      "changeInWorkingCapital": -2694000000,
      "accountsReceivables": -3561000000,
      "inventory": -977000000,
      "accountsPayables": 1689000000,
      "otherWorkingCapital": 155000000,
      "otherNonCashItems": -115000000,
      "netCashProvidedByOperatingActivities": 17627000000,
      "investmentsInPropertyPlantAndEquipment": -813000000,
      "acquisitionsNet": -148000000,
      "purchasesOfInvestments": -4992000000,
      "salesMaturitiesOfInvestments": 1607000000,
      "otherInvestingActivites": 0,
      "netCashUsedForInvestingActivites": -4346000000,
      "debtRepayment": 0,
      "commonStockIssued": 0,
      "commonStockRepurchased": -10997000000,
      "dividendsPaid": -245000000,
      "otherFinancingActivites": -1503000000,
      "netCashUsedProvidedByFinancingActivities": -12745000000,
      "effectOfForexChangesOnCash": 0,
      "netChangeInCash": 536000000,
      "cashAtEndOfPeriod": 9107000000,
      "cashAtBeginningOfPeriod": 8571000000,
      "operatingCashFlow": 17627000000,
      "capitalExpenditure": -813000000,
      "freeCashFlow": 16814000000,
      "link": "https://www.sec.gov/Archives/edgar/data/1045810/000104581024000316/0001045810-24-000316-index.htm",
      "finalLink": "https://www.sec.gov/Archives/edgar/data/1045810/000104581024000316/nvda-20241027.htm"
    },
    {
      "date": "2024-07-28",
      "symbol": "NVDA",
      "reportedCurrency": "USD",
      "cik": "0001045810",
      "fillingDate": "2024-08-28",
      "acceptedDate": "2024-08-28 17:05:08",
      "calendarYear": "2025",
      "period": "Q2",
      "netIncome": 16599000000,
      "depreciationAndAmortization": 433000000,
      "deferredIncomeTax": -1699000000,
      "stockBasedCompensation": 1153000000,
      "changeInWorkingCapital": -1660000000,
      "accountsReceivables": -1767000000,
      "inventory": -803000000,
      "accountsPayables": 823000000,
      "otherWorkingCapital": 87000000,
      "otherNonCashItems": -338000000,
      "netCashProvidedByOperatingActivities": 14488000000,
      "investmentsInPropertyPlantAndEquipment": -977000000,
      "acquisitionsNet": -278000000,
      "purchasesOfInvestments": -6143000000,
      "salesMaturitiesOfInvestments": 4214000000,
      "otherInvestingActivites": 0,
      "netCashUsedForInvestingActivites": -3184000000,
      "debtRepayment": -1250000000,
      "commonStockIssued": 0,
      "commonStockRepurchased": -7158000000,
      "dividendsPaid": -246000000,
      "otherFinancingActivites": -1666000000,
      "netCashUsedProvidedByFinancingActivities": -10320000000,
      "effectOfForexChangesOnCash": 0,
      "netChangeInCash": 984000000,
      "cashAtEndOfPeriod": 8571000000,
      "cashAtBeginningOfPeriod": 7587000000,
      "operatingCashFlow": 14488000000,
      "capitalExpenditure": -977000000,
      "freeCashFlow": 13511000000,
      "link": "https://www.sec.gov/Archives/edgar/data/1045810/000104581024000264/0001045810-24-000264-index.htm",
      "finalLink": "https://www.sec.gov/Archives/edgar/data/1045810/000104581024000264/nvda-20240728.htm"
    },
    {
      "date": "2024-04-28",
      "symbol": "NVDA",
      "reportedCurrency": "USD",
      "cik": "0001045810",
      "fillingDate": "2024-05-29",
      "acceptedDate": "2024-05-29 16:36:32",
      "calendarYear": "2025",
      "period": "Q1",
      "netIncome": 14881000000,
      "depreciationAndAmortization": 410000000,
      "deferredIncomeTax": -1577000000,
      "stockBasedCompensation": 1011000000,
      "changeInWorkingCapital": 834000000,
      "accountsReceivables": -2366000000,
      "inventory": -577000000,
      "accountsPayables": -22000000,
      "otherWorkingCapital": 3799000000,
      "otherNonCashItems": -214000000,
      "netCashProvidedByOperatingActivities": 15345000000,
      "investmentsInPropertyPlantAndEquipment": -369000000,
      "acquisitionsNet": -39000000,
      "purchasesOfInvestments": -9438000000,
      "salesMaturitiesOfInvestments": 4153000000,
      "otherInvestingActivites": 0,
      "netCashUsedForInvestingActivites": -5693000000,
      "debtRepayment": 0,
      "commonStockIssued": 0,
      "commonStockRepurchased": -7740000000,
      "dividendsPaid": -98000000,
      "otherFinancingActivites": -1507000000,
      "netCashUsedProvidedByFinancingActivities": -9345000000,
      "effectOfForexChangesOnCash": 0,
      "netChangeInCash": 307000000,
      "cashAtEndOfPeriod": 7587000000,
      "cashAtBeginningOfPeriod": 7280000000,
      "operatingCashFlow": 15345000000,
      "capitalExpenditure": -369000000,
      "freeCashFlow": 14976000000,
      "link": "https://www.sec.gov/Archives/edgar/data/1045810/000104581024000124/0001045810-24-000124-index.htm",
      "finalLink": "https://www.sec.gov/Archives/edgar/data/1045810/000104581024000124/nvda-20240428.htm"
    },
    {
      "date": "2024-01-28",
      "symbol": "NVDA",
      "reportedCurrency": "USD",
      "cik": "0001045810",
      "fillingDate": "2024-02-21",
      "acceptedDate": "2024-02-21 16:36:57",
      "calendarYear": "2024",
      "period": "Q4",
      "netIncome": 12285000000,
      "depreciationAndAmortization": 387000000,
      "deferredIncomeTax": -78000000,
      "stockBasedCompensation": 994000000,
      "changeInWorkingCapital": -1719000000,
      "accountsReceivables": -1690000000,
      "inventory": -503000000,
      "accountsPayables": 281000000,
      "otherWorkingCapital": 193000000,
      "otherNonCashItems": -370000000,
      "netCashProvidedByOperatingActivities": 11499000000,
      "investmentsInPropertyPlantAndEquipment": -254000000,
      "acquisitionsNet": 0,
      "purchasesOfInvestments": -7636000000,
      "salesMaturitiesOfInvestments": 1781000000,
      "otherInvestingActivites": 0,
      "netCashUsedForInvestingActivites": -6109000000,
      "debtRepayment": 1250000000,
      "commonStockIssued": 0,
      "commonStockRepurchased": -2659000000,
      "dividendsPaid": -99000000,
      "otherFinancingActivites": -2121000000,
      "netCashUsedProvidedByFinancingActivities": -3629000000,
      "effectOfForexChangesOnCash": 0,
      "netChangeInCash": 1761000000,
      "cashAtEndOfPeriod": 7280000000,
      "cashAtBeginningOfPeriod": 5519000000,
      "operatingCashFlow": 11499000000,
      "capitalExpenditure": -254000000,
      "freeCashFlow": 11245000000,
      "link": "https://www.sec.gov/Archives/edgar/data/1045810/000104581024000029/0001045810-24-000029-index.htm",
      "finalLink": "https://www.sec.gov/Archives/edgar/data/1045810/000104581024000029/nvda-20240128.htm"
    },
    {
      "date": "2023-10-29",
      "symbol": "NVDA",
      "reportedCurrency": "USD",
      "cik": "0001045810",
      "fillingDate": "2023-11-21",
      "acceptedDate": "2023-11-21 16:36:29",
      "calendarYear": "2024",
      "period": "Q3",
      "netIncome": 9243000000,
      "depreciationAndAmortization": 372000000,
      "deferredIncomeTax": -530000000,
      "stockBasedCompensation": 979000000,
      "changeInWorkingCapital": -2733000000,
      "accountsReceivables": -1243000000,
      "inventory": -456000000,
      "accountsPayables": 461000000,
      "otherWorkingCapital": -1495000000,
      "otherNonCashItems": 1000000,
      "netCashProvidedByOperatingActivities": 7332000000,
      "investmentsInPropertyPlantAndEquipment": -278000000,
      "acquisitionsNet": 456000000,
      "purchasesOfInvestments": -6242000000,
      "salesMaturitiesOfInvestments": 2890000000,
      "otherInvestingActivites": 4000000,
      "netCashUsedForInvestingActivites": -3170000000,
      "debtRepayment": 0,
      "commonStockIssued": 0,
      "commonStockRepurchased": -3807000000,
      "dividendsPaid": -97000000,
      "otherFinancingActivites": -621000000,
      "netCashUsedProvidedByFinancingActivities": -4525000000,
      "effectOfForexChangesOnCash": 0,
      "netChangeInCash": -363000000,
      "cashAtEndOfPeriod": 5519000000,
      "cashAtBeginningOfPeriod": 5882000000,
      "operatingCashFlow": 7332000000,
      "capitalExpenditure": -278000000,
      "freeCashFlow": 7054000000,
      "link": "https://www.sec.gov/Archives/edgar/data/1045810/000104581023000227/0001045810-23-000227-index.htm",
      "finalLink": "https://www.sec.gov/Archives/edgar/data/1045810/000104581023000227/nvda-20231029.htm"
    },
    {
      "date": "2023-07-30",
      "symbol": "NVDA",
      "reportedCurrency": "USD",
      "cik": "0001045810",
      "fillingDate": "2023-08-28",
      "acceptedDate": "2023-08-25 19:36:34",
      "calendarYear": "2024",
      "period": "Q2",
      "netIncome": 6189000000,
      "depreciationAndAmortization": 365000000,
      "deferredIncomeTax": -746000000,
      "stockBasedCompensation": 841000000,
      "changeInWorkingCapital": -174000000,
      "accountsReceivables": -2987000000,
      "inventory": 295000000,
      "accountsPayables": 778000000,
      "otherWorkingCapital": 1740000000,
      "otherNonCashItems": -127000000,
      "netCashProvidedByOperatingActivities": 6348000000,
      "investmentsInPropertyPlantAndEquipment": -289000000,
      "acquisitionsNet": -235000000,
      "purchasesOfInvestments": -2542000000,
      "salesMaturitiesOfInvestments": 2599000000,
      "otherInvestingActivites": 21000000,
      "netCashUsedForInvestingActivites": -446000000,
      "debtRepayment": -1250000000,
      "commonStockIssued": 0,
      "commonStockRepurchased": -3067000000,
      "dividendsPaid": -100000000,
      "otherFinancingActivites": -682000000,
      "netCashUsedProvidedByFinancingActivities": -5099000000,
      "effectOfForexChangesOnCash": 0,
      "netChangeInCash": 803000000,
      "cashAtEndOfPeriod": 5882000000,
      "cashAtBeginningOfPeriod": 5079000000,
      "operatingCashFlow": 6348000000,
      "capitalExpenditure": -289000000,
      "freeCashFlow": 6059000000,
      "link": "https://www.sec.gov/Archives/edgar/data/1045810/000104581023000175/0001045810-23-000175-index.htm",
      "finalLink": "https://www.sec.gov/Archives/edgar/data/1045810/000104581023000175/nvda-20230730.htm"
    },
    {
      "date": "2023-04-30",
      "symbol": "NVDA",
      "reportedCurrency": "USD",
      "cik": "0001045810",
      "fillingDate": "2023-05-26",
      "acceptedDate": "2023-05-26 16:17:32",
      "calendarYear": "2024",
      "period": "Q1",
      "netIncome": 2043000000,
      "depreciationAndAmortization": 384000000,
      "deferredIncomeTax": -1135000000,
      "stockBasedCompensation": 735000000,
      "changeInWorkingCapital": 904000000,
      "accountsReceivables": -252000000,
      "inventory": 566000000,
      "accountsPayables": 11000000,
      "otherWorkingCapital": 579000000,
      "otherNonCashItems": -20000000,
      "netCashProvidedByOperatingActivities": 2911000000,
      "investmentsInPropertyPlantAndEquipment": -248000000,
      "acquisitionsNet": -304000000,
      "purchasesOfInvestments": -2801000000,
      "salesMaturitiesOfInvestments": 2512000000,
      "otherInvestingActivites": 0,
      "netCashUsedForInvestingActivites": -841000000,
      "debtRepayment": 0,
      "commonStockIssued": 246000000,
      "commonStockRepurchased": 0,
      "dividendsPaid": -99000000,
      "otherFinancingActivites": -527000000,
      "netCashUsedProvidedByFinancingActivities": -380000000,
      "effectOfForexChangesOnCash": 0,
      "netChangeInCash": 1690000000,
      "cashAtEndOfPeriod": 5079000000,
      "cashAtBeginningOfPeriod": 3389000000,
      "operatingCashFlow": 2911000000,
      "capitalExpenditure": -248000000,
      "freeCashFlow": 2663000000,
      "link": "https://www.sec.gov/Archives/edgar/data/1045810/000104581023000093/0001045810-23-000093-index.htm",
      "finalLink": "https://www.sec.gov/Archives/edgar/data/1045810/000104581023000093/nvda-20230430.htm"
    },
    {
      "date": "2023-01-29",
      "symbol": "NVDA",
      "reportedCurrency": "USD",
      "cik": "0001045810",
      "fillingDate": "2023-02-24",
      "acceptedDate": "2023-02-24 17:23:43",
      "calendarYear": "2023",
      "period": "Q4",
      "netIncome": 1414000000,
      "depreciationAndAmortization": 426000000,
      "deferredIncomeTax": -647000000,
      "stockBasedCompensation": 738000000,
      "changeInWorkingCapital": 287000000,
      "accountsReceivables": 1080000000,
      "inventory": -706000000,
      "accountsPayables": -193000000,
      "otherWorkingCapital": 106000000,
      "otherNonCashItems": 30000000,
      "netCashProvidedByOperatingActivities": 2248000000,
      "investmentsInPropertyPlantAndEquipment": -509000000,
      "acquisitionsNet": 0,
      "purchasesOfInvestments": -2127000000,
      "salesMaturitiesOfInvestments": 2633000000,
      "otherInvestingActivites": 0,
      "netCashUsedForInvestingActivites": -3000000,
      "debtRepayment": 0,
      "commonStockIssued": 0,
      "commonStockRepurchased": -1213000000,
      "dividendsPaid": -98000000,
      "otherFinancingActivites": -345000000,
      "netCashUsedProvidedByFinancingActivities": -1656000000,
      "effectOfForexChangesOnCash": 0,
      "netChangeInCash": 589000000,
      "cashAtEndOfPeriod": 3389000000,
      "cashAtBeginningOfPeriod": 2800000000,
      "operatingCashFlow": 2248000000,
      "capitalExpenditure": -509000000,
      "freeCashFlow": 1739000000,
      "link": "https://www.sec.gov/Archives/edgar/data/1045810/000104581023000017/0001045810-23-000017-index.htm",
      "finalLink": "https://www.sec.gov/Archives/edgar/data/1045810/000104581023000017/nvda-20230129.htm"
    },
    {
      "date": "2022-10-30",
      "symbol": "NVDA",
      "reportedCurrency": "USD",
      "cik": "0001045810",
      "fillingDate": "2022-11-18",
      "acceptedDate": "2022-11-18 16:35:31",
      "calendarYear": "2023",
      "period": "Q3",
      "netIncome": 680000000,
      "depreciationAndAmortization": 406000000,
      "deferredIncomeTax": -532000000,
      "stockBasedCompensation": 745000000,
      "changeInWorkingCapital": -873000000,
      "accountsReceivables": 410000000,
      "inventory": -563000000,
      "accountsPayables": -917000000,
      "otherWorkingCapital": 197000000,
      "otherNonCashItems": -34000000,
      "netCashProvidedByOperatingActivities": 392000000,
      "investmentsInPropertyPlantAndEquipment": -530000000,
      "acquisitionsNet": 0,
      "purchasesOfInvestments": -2206000000,
      "salesMaturitiesOfInvestments": 5884000000,
      "otherInvestingActivites": 0,
      "netCashUsedForInvestingActivites": 3148000000,
      "debtRepayment": 0,
      "commonStockIssued": 0,
      "commonStockRepurchased": -3485000000,
      "dividendsPaid": -100000000,
      "otherFinancingActivites": -168000000,
      "netCashUsedProvidedByFinancingActivities": -3753000000,
      "effectOfForexChangesOnCash": 0,
      "netChangeInCash": -213000000,
      "cashAtEndOfPeriod": 2800000000,
      "cashAtBeginningOfPeriod": 3013000000,
      "operatingCashFlow": 392000000,
      "capitalExpenditure": -530000000,
      "freeCashFlow": -138000000,
      "link": "https://www.sec.gov/Archives/edgar/data/1045810/000104581022000166/0001045810-22-000166-index.htm",
      "finalLink": "https://www.sec.gov/Archives/edgar/data/1045810/000104581022000166/nvda-20221030.htm"
    },
    {
      "date": "2022-07-31",
      "symbol": "NVDA",
      "reportedCurrency": "USD",
      "cik": "0001045810",
      "fillingDate": "2022-08-31",
      "acceptedDate": "2022-08-31 17:01:35",
      "calendarYear": "2023",
      "period": "Q2",
      "netIncome": 656000000,
      "depreciationAndAmortization": 378000000,
      "deferredIncomeTax": -443000000,
      "stockBasedCompensation": 648000000,
      "changeInWorkingCapital": 29000000,
      "accountsReceivables": 120000000,
      "inventory": -725000000,
      "accountsPayables": 304000000,
      "otherWorkingCapital": 330000000,
      "otherNonCashItems": 2000000,
      "netCashProvidedByOperatingActivities": 1270000000,
      "investmentsInPropertyPlantAndEquipment": -433000000,
      "acquisitionsNet": -13000000,
      "purchasesOfInvestments": -3674000000,
      "salesMaturitiesOfInvestments": 5738000000,
      "otherInvestingActivites": 0,
      "netCashUsedForInvestingActivites": 1618000000,
      "debtRepayment": 0,
      "commonStockIssued": 0,
      "commonStockRepurchased": -3345000000,
      "dividendsPaid": -100000000,
      "otherFinancingActivites": -317000000,
      "netCashUsedProvidedByFinancingActivities": -3762000000,
      "effectOfForexChangesOnCash": 0,
      "netChangeInCash": -874000000,
      "cashAtEndOfPeriod": 3013000000,
      "cashAtBeginningOfPeriod": 3887000000,
      "operatingCashFlow": 1270000000,
      "capitalExpenditure": -433000000,
      "freeCashFlow": 837000000,
      "link": "https://www.sec.gov/Archives/edgar/data/1045810/000104581022000147/0001045810-22-000147-index.htm",
      "finalLink": "https://www.sec.gov/Archives/edgar/data/1045810/000104581022000147/nvda-20220731.htm"
    },
    {
      "date": "2022-05-01",
      "symbol": "NVDA",
      "reportedCurrency": "USD",
      "cik": "0001045810",
      "fillingDate": "2022-05-27",
      "acceptedDate": "2022-05-27 16:21:55",
      "calendarYear": "2023",
      "period": "Q1",
      "netIncome": 1618000000,
      "depreciationAndAmortization": 334000000,
      "deferredIncomeTax": -542000000,
      "stockBasedCompensation": 578000000,
      "changeInWorkingCapital": -1650000000,
      "accountsReceivables": -788000000,
      "inventory": -560000000,
      "accountsPayables": 255000000,
      "otherWorkingCapital": -557000000,
      "otherNonCashItems": 1393000000,
      "netCashProvidedByOperatingActivities": 1731000000,
      "investmentsInPropertyPlantAndEquipment": -361000000,
      "acquisitionsNet": -36000000,
      "purchasesOfInvestments": -3967000000,
      "salesMaturitiesOfInvestments": 6976000000,
      "otherInvestingActivites": 0,
      "netCashUsedForInvestingActivites": 2612000000,
      "debtRepayment": -22000000,
      "commonStockIssued": 0,
      "commonStockRepurchased": -1996000000,
      "dividendsPaid": -100000000,
      "otherFinancingActivites": -328000000,
      "netCashUsedProvidedByFinancingActivities": -2446000000,
      "effectOfForexChangesOnCash": 0,
      "netChangeInCash": 1897000000,
      "cashAtEndOfPeriod": 3887000000,
      "cashAtBeginningOfPeriod": 1990000000,
      "operatingCashFlow": 1731000000,
      "capitalExpenditure": -361000000,
      "freeCashFlow": 1370000000,
      "link": "https://www.sec.gov/Archives/edgar/data/1045810/000104581022000079/0001045810-22-000079-index.htm",
      "finalLink": "https://www.sec.gov/Archives/edgar/data/1045810/000104581022000079/nvda-20220501.htm"
    },
    {
      "date": "2022-01-30",
      "symbol": "NVDA",
      "reportedCurrency": "USD",
      "cik": "0001045810",
      "fillingDate": "2022-03-18",
      "acceptedDate": "2022-03-17 20:33:34",
      "calendarYear": "2022",
      "period": "Q4",
      "netIncome": 3003000000,
      "depreciationAndAmortization": 309000000,
      "deferredIncomeTax": -224000000,
      "stockBasedCompensation": 551000000,
      "changeInWorkingCapital": -680000000,
      "accountsReceivables": -692000000,
      "inventory": -374000000,
      "accountsPayables": 94000000,
      "otherWorkingCapital": 292000000,
      "otherNonCashItems": 74000000,
      "netCashProvidedByOperatingActivities": 3033000000,
      "investmentsInPropertyPlantAndEquipment": -273000000,
      "acquisitionsNet": -60000000,
      "purchasesOfInvestments": -8777000000,
      "salesMaturitiesOfInvestments": 7524000000,
      "otherInvestingActivites": 0,
      "netCashUsedForInvestingActivites": -1586000000,
      "debtRepayment": 0,
      "commonStockIssued": 4000000,
      "commonStockRepurchased": 0,
      "dividendsPaid": -101000000,
      "otherFinancingActivites": -648000000,
      "netCashUsedProvidedByFinancingActivities": -745000000,
      "effectOfForexChangesOnCash": 0,
      "netChangeInCash": 702000000,
      "cashAtEndOfPeriod": 1990000000,
      "cashAtBeginningOfPeriod": 1288000000,
      "operatingCashFlow": 3033000000,
      "capitalExpenditure": -273000000,
      "freeCashFlow": 2760000000,
      "link": "https://www.sec.gov/Archives/edgar/data/1045810/000104581022000036/0001045810-22-000036-index.htm",
      "finalLink": "https://www.sec.gov/Archives/edgar/data/1045810/000104581022000036/nvda-20220130.htm"
    },
    {
      "date": "2021-10-31",
      "symbol": "NVDA",
      "reportedCurrency": "USD",
      "cik": "0001045810",
      "fillingDate": "2021-11-22",
      "acceptedDate": "2021-11-19 21:16:20",
      "calendarYear": "2022",
      "period": "Q3",
      "netIncome": 2464000000,
      "depreciationAndAmortization": 298000000,
      "deferredIncomeTax": -21000000,
      "stockBasedCompensation": 559000000,
      "changeInWorkingCapital": -1771000000,
      "accountsReceivables": -366000000,
      "inventory": -118000000,
      "accountsPayables": 140000000,
      "otherWorkingCapital": -1427000000,
      "otherNonCashItems": -10000000,
      "netCashProvidedByOperatingActivities": 1519000000,
      "investmentsInPropertyPlantAndEquipment": -222000000,
      "acquisitionsNet": -203000000,
      "purchasesOfInvestments": -6766000000,
      "salesMaturitiesOfInvestments": 2752000000,
      "otherInvestingActivites": 0,
      "netCashUsedForInvestingActivites": -4439000000,
      "debtRepayment": -1008000000,
      "commonStockIssued": 149000000,
      "commonStockRepurchased": 0,
      "dividendsPaid": -100000000,
      "otherFinancingActivites": -461000000,
      "netCashUsedProvidedByFinancingActivities": -1420000000,
      "effectOfForexChangesOnCash": 0,
      "netChangeInCash": -4340000000,
      "cashAtEndOfPeriod": 1288000000,
      "cashAtBeginningOfPeriod": 5628000000,
      "operatingCashFlow": 1519000000,
      "capitalExpenditure": -222000000,
      "freeCashFlow": 1297000000,
      "link": "https://www.sec.gov/Archives/edgar/data/1045810/000104581021000163/0001045810-21-000163-index.htm",
      "finalLink": "https://www.sec.gov/Archives/edgar/data/1045810/000104581021000163/nvda-20211031.htm"
    },
    {
      "date": "2021-08-01",
      "symbol": "NVDA",
      "reportedCurrency": "USD",
      "cik": "0001045810",
      "fillingDate": "2021-08-20",
      "acceptedDate": "2021-08-20 16:32:40",
      "calendarYear": "2022",
      "period": "Q2",
      "netIncome": 2373000000,
      "depreciationAndAmortization": 286000000,
      "deferredIncomeTax": -185000000,
      "stockBasedCompensation": 465000000,
      "changeInWorkingCapital": -276000000,
      "accountsReceivables": -562000000,
      "inventory": -123000000,
      "accountsPayables": 209000000,
      "otherWorkingCapital": 200000000,
      "otherNonCashItems": 19000000,
      "netCashProvidedByOperatingActivities": 2682000000,
      "investmentsInPropertyPlantAndEquipment": -183000000,
      "acquisitionsNet": 0,
      "purchasesOfInvestments": -4796000000,
      "salesMaturitiesOfInvestments": 2446000000,
      "otherInvestingActivites": 0,
      "netCashUsedForInvestingActivites": -2533000000,
      "debtRepayment": 5004000000,
      "commonStockIssued": 2000000,
      "commonStockRepurchased": 0,
      "dividendsPaid": -99000000,
      "otherFinancingActivites": -406000000,
      "netCashUsedProvidedByFinancingActivities": 4501000000,
      "effectOfForexChangesOnCash": 0,
      "netChangeInCash": 4650000000,
      "cashAtEndOfPeriod": 5628000000,
      "cashAtBeginningOfPeriod": 978000000,
      "operatingCashFlow": 2682000000,
      "capitalExpenditure": -183000000,
      "freeCashFlow": 2499000000,
      "link": "https://www.sec.gov/Archives/edgar/data/1045810/000104581021000131/0001045810-21-000131-index.htm",
      "finalLink": "https://www.sec.gov/Archives/edgar/data/1045810/000104581021000131/nvda-20210801.htm"
    },
    {
      "date": "2021-05-02",
      "symbol": "NVDA",
      "reportedCurrency": "USD",
      "cik": "0001045810",
      "fillingDate": "2021-05-26",
      "acceptedDate": "2021-05-26 16:35:56",
      "calendarYear": "2022",
      "period": "Q1",
      "netIncome": 1912000000,
      "depreciationAndAmortization": 281000000,
      "deferredIncomeTax": 24000000,
      "stockBasedCompensation": 429000000,
      "changeInWorkingCapital": -636000000,
      "accountsReceivables": -595000000,
      "inventory": -159000000,
      "accountsPayables": 36000000,
      "otherWorkingCapital": 82000000,
      "otherNonCashItems": -136000000,
      "netCashProvidedByOperatingActivities": 1874000000,
      "investmentsInPropertyPlantAndEquipment": -298000000,
      "acquisitionsNet": 0,
      "purchasesOfInvestments": -4472000000,
      "salesMaturitiesOfInvestments": 3498000000,
      "otherInvestingActivites": 0,
      "netCashUsedForInvestingActivites": -1272000000,
      "debtRepayment": -19000000,
      "commonStockIssued": 126000000,
      "commonStockRepurchased": 0,
      "dividendsPaid": -99000000,
      "otherFinancingActivites": -479000000,
      "netCashUsedProvidedByFinancingActivities": -471000000,
      "effectOfForexChangesOnCash": 0,
      "netChangeInCash": 131000000,
      "cashAtEndOfPeriod": 978000000,
      "cashAtBeginningOfPeriod": 847000000,
      "operatingCashFlow": 1874000000,
      "capitalExpenditure": -298000000,
      "freeCashFlow": 1576000000,
      "link": "https://www.sec.gov/Archives/edgar/data/1045810/000104581021000064/0001045810-21-000064-index.htm",
      "finalLink": "https://www.sec.gov/Archives/edgar/data/1045810/000104581021000064/nvda-20210502.htm"
    },
    {
      "date": "2021-01-31",
      "symbol": "NVDA",
      "reportedCurrency": "USD",
      "cik": "0001045810",
      "fillingDate": "2021-02-26",
      "acceptedDate": "2021-02-26 17:03:14",
      "calendarYear": "2021",
      "period": "Q4",
      "netIncome": 1457000000,
      "depreciationAndAmortization": 288000000,
      "deferredIncomeTax": -165000000,
      "stockBasedCompensation": 416000000,
      "changeInWorkingCapital": 89000000,
      "accountsReceivables": 117000000,
      "inventory": -334000000,
      "accountsPayables": 74000000,
      "otherWorkingCapital": 232000000,
      "otherNonCashItems": -18000000,
      "netCashProvidedByOperatingActivities": 2067000000,
      "investmentsInPropertyPlantAndEquipment": -283000000,
      "acquisitionsNet": 0,
      "purchasesOfInvestments": -6498000000,
      "salesMaturitiesOfInvestments": 3652000000,
      "otherInvestingActivites": 0,
      "netCashUsedForInvestingActivites": -3129000000,
      "debtRepayment": -3000000,
      "commonStockIssued": 4000000,
      "commonStockRepurchased": 0,
      "dividendsPaid": -99000000,
      "otherFinancingActivites": -244000000,
      "netCashUsedProvidedByFinancingActivities": -342000000,
      "effectOfForexChangesOnCash": 0,
      "netChangeInCash": -1404000000,
      "cashAtEndOfPeriod": 847000000,
      "cashAtBeginningOfPeriod": 2251000000,
      "operatingCashFlow": 2067000000,
      "capitalExpenditure": -283000000,
      "freeCashFlow": 1784000000,
      "link": "https://www.sec.gov/Archives/edgar/data/1045810/000104581021000010/0001045810-21-000010-index.htm",
      "finalLink": "https://www.sec.gov/Archives/edgar/data/1045810/000104581021000010/nvda-20210131.htm"
    },
    {
      "date": "2020-10-25",
      "symbol": "NVDA",
      "reportedCurrency": "USD",
      "cik": "0001045810",
      "fillingDate": "2020-11-18",
      "acceptedDate": "2020-11-18 16:35:57",
      "calendarYear": "2021",
      "period": "Q3",
      "netIncome": 1336000000,
      "depreciationAndAmortization": 299000000,
      "deferredIncomeTax": -53000000,
      "stockBasedCompensation": 383000000,
      "changeInWorkingCapital": -689000000,
      "accountsReceivables": -462000000,
      "inventory": -93000000,
      "accountsPayables": 226000000,
      "otherWorkingCapital": -360000000,
      "otherNonCashItems": 3000000,
      "netCashProvidedByOperatingActivities": 1279000000,
      "investmentsInPropertyPlantAndEquipment": -473000000,
      "acquisitionsNet": -1353000000,
      "purchasesOfInvestments": -4551000000,
      "salesMaturitiesOfInvestments": 4376000000,
      "otherInvestingActivites": 0,
      "netCashUsedForInvestingActivites": -2001000000,
      "debtRepayment": 0,
      "commonStockIssued": 96000000,
      "commonStockRepurchased": 0,
      "dividendsPaid": -99000000,
      "otherFinancingActivites": -298000000,
      "netCashUsedProvidedByFinancingActivities": -301000000,
      "effectOfForexChangesOnCash": 0,
      "netChangeInCash": -1023000000,
      "cashAtEndOfPeriod": 2251000000,
      "cashAtBeginningOfPeriod": 3274000000,
      "operatingCashFlow": 1279000000,
      "capitalExpenditure": -473000000,
      "freeCashFlow": 806000000,
      "link": "https://www.sec.gov/Archives/edgar/data/1045810/000104581020000189/0001045810-20-000189-index.htm",
      "finalLink": "https://www.sec.gov/Archives/edgar/data/1045810/000104581020000189/nvda-20201025.htm"
    },
    {
      "date": "2020-07-26",
      "symbol": "NVDA",
      "reportedCurrency": "USD",
      "cik": "0001045810",
      "fillingDate": "2020-08-19",
      "acceptedDate": "2020-08-19 16:36:51",
      "calendarYear": "2021",
      "period": "Q2",
      "netIncome": 622000000,
      "depreciationAndAmortization": 404000000,
      "deferredIncomeTax": -80000000,
      "stockBasedCompensation": 374000000,
      "changeInWorkingCapital": 256000000,
      "accountsReceivables": 44000000,
      "inventory": 54000000,
      "accountsPayables": -8000000,
      "otherWorkingCapital": 166000000,
      "otherNonCashItems": -9000000,
      "netCashProvidedByOperatingActivities": 1567000000,
      "investmentsInPropertyPlantAndEquipment": -217000000,
      "acquisitionsNet": -7137000000,
      "purchasesOfInvestments": -7426000000,
      "salesMaturitiesOfInvestments": 1290000000,
      "otherInvestingActivites": 0,
      "netCashUsedForInvestingActivites": -13490000000,
      "debtRepayment": -8000000,
      "commonStockIssued": 6000000,
      "commonStockRepurchased": 0,
      "dividendsPaid": -99000000,
      "otherFinancingActivites": -196000000,
      "netCashUsedProvidedByFinancingActivities": -297000000,
      "effectOfForexChangesOnCash": 0,
      "netChangeInCash": -12220000000,
      "cashAtEndOfPeriod": 3274000000,
      "cashAtBeginningOfPeriod": 15494000000,
      "operatingCashFlow": 1567000000,
      "capitalExpenditure": -217000000,
      "freeCashFlow": 1350000000,
      "link": "https://www.sec.gov/Archives/edgar/data/1045810/000104581020000147/0001045810-20-000147-index.htm",
      "finalLink": "https://www.sec.gov/Archives/edgar/data/1045810/000104581020000147/nvda-20200726.htm"
    },
    {
      "date": "2020-04-26",
      "symbol": "NVDA",
      "reportedCurrency": "USD",
      "cik": "0001045810",
      "fillingDate": "2020-05-21",
      "acceptedDate": "2020-05-21 16:32:58",
      "calendarYear": "2021",
      "period": "Q1",
      "netIncome": 917000000,
      "depreciationAndAmortization": 107000000,
      "deferredIncomeTax": 16000000,
      "stockBasedCompensation": 224000000,
      "changeInWorkingCapital": -359000000,
      "accountsReceivables": -249000000,
      "inventory": -151000000,
      "accountsPayables": 71000000,
      "otherWorkingCapital": -30000000,
      "otherNonCashItems": 4000000,
      "netCashProvidedByOperatingActivities": 909000000,
      "investmentsInPropertyPlantAndEquipment": -155000000,
      "acquisitionsNet": -34000000,
      "purchasesOfInvestments": -867000000,
      "salesMaturitiesOfInvestments": 1000000,
      "otherInvestingActivites": 0,
      "netCashUsedForInvestingActivites": -1055000000,
      "debtRepayment": 4979000000,
      "commonStockIssued": 88000000,
      "commonStockRepurchased": 0,
      "dividendsPaid": -98000000,
      "otherFinancingActivites": -225000000,
      "netCashUsedProvidedByFinancingActivities": 4744000000,
      "effectOfForexChangesOnCash": 0,
      "netChangeInCash": 4598000000,
      "cashAtEndOfPeriod": 15494000000,
      "cashAtBeginningOfPeriod": 10896000000,
      "operatingCashFlow": 909000000,
      "capitalExpenditure": -155000000,
      "freeCashFlow": 754000000,
      "link": "https://www.sec.gov/Archives/edgar/data/1045810/000104581020000065/0001045810-20-000065-index.htm",
      "finalLink": "https://www.sec.gov/Archives/edgar/data/1045810/000104581020000065/nvda-20200426.htm"
    },
    {
      "date": "2020-01-26",
      "symbol": "NVDA",
      "reportedCurrency": "USD",
      "cik": "0001045810",
      "fillingDate": "2020-02-20",
      "acceptedDate": "2020-02-20 16:38:18",
      "calendarYear": "2020",
      "period": "Q4",
      "netIncome": 951000000,
      "depreciationAndAmortization": 106000000,
      "deferredIncomeTax": 23000000,
      "stockBasedCompensation": 220000000,
      "changeInWorkingCapital": 165000000,
      "accountsReceivables": -201000000,
      "inventory": 66000000,
      "accountsPayables": 103000000,
      "otherWorkingCapital": 197000000,
      "otherNonCashItems": 0,
      "netCashProvidedByOperatingActivities": 1465000000,
      "investmentsInPropertyPlantAndEquipment": -145000000,
      "acquisitionsNet": 0,
      "purchasesOfInvestments": -8000000,
      "salesMaturitiesOfInvestments": 2000000,
      "otherInvestingActivites": 0,
      "netCashUsedForInvestingActivites": -151000000,
      "debtRepayment": 0,
      "commonStockIssued": 3000000,
      "commonStockRepurchased": 0,
      "dividendsPaid": -98000000,
      "otherFinancingActivites": -88000000,
      "netCashUsedProvidedByFinancingActivities": -183000000,
      "effectOfForexChangesOnCash": 0,
      "netChangeInCash": 1131000000,
      "cashAtEndOfPeriod": 10896000000,
      "cashAtBeginningOfPeriod": 9765000000,
      "operatingCashFlow": 1465000000,
      "capitalExpenditure": -145000000,
      "freeCashFlow": 1320000000,
      "link": "https://www.sec.gov/Archives/edgar/data/1045810/000104581020000010/0001045810-20-000010-index.htm",
      "finalLink": "https://www.sec.gov/Archives/edgar/data/1045810/000104581020000010/nvda-2020x10k.htm"
    },
    {
      "date": "2019-10-27",
      "symbol": "NVDA",
      "reportedCurrency": "USD",
      "cik": "0001045810",
      "fillingDate": "2019-11-14",
      "acceptedDate": "2019-11-14 16:36:33",
      "calendarYear": "2020",
      "period": "Q3",
      "netIncome": 898000000,
      "depreciationAndAmortization": 92000000,
      "deferredIncomeTax": 22000000,
      "stockBasedCompensation": 223000000,
      "changeInWorkingCapital": 401000000,
      "accountsReceivables": 105000000,
      "inventory": 153000000,
      "accountsPayables": 136000000,
      "otherWorkingCapital": 7000000,
      "otherNonCashItems": 4000000,
      "netCashProvidedByOperatingActivities": 1640000000,
      "investmentsInPropertyPlantAndEquipment": -103000000,
      "acquisitionsNet": 0,
      "purchasesOfInvestments": -4000000,
      "salesMaturitiesOfInvestments": 1363000000,
      "otherInvestingActivites": 0,
      "netCashUsedForInvestingActivites": 1256000000,
      "debtRepayment": 0,
      "commonStockIssued": 63000000,
      "commonStockRepurchased": 0,
      "dividendsPaid": -97000000,
      "otherFinancingActivites": -202000000,
      "netCashUsedProvidedByFinancingActivities": -236000000,
      "effectOfForexChangesOnCash": 0,
      "netChangeInCash": 2660000000,
      "cashAtEndOfPeriod": 9765000000,
      "cashAtBeginningOfPeriod": 7105000000,
      "operatingCashFlow": 1640000000,
      "capitalExpenditure": -103000000,
      "freeCashFlow": 1537000000,
      "link": "https://www.sec.gov/Archives/edgar/data/1045810/000104581019000170/0001045810-19-000170-index.htm",
      "finalLink": "https://www.sec.gov/Archives/edgar/data/1045810/000104581019000170/nvda2020q310q.htm"
    },
    {
      "date": "2019-07-28",
      "symbol": "NVDA",
      "reportedCurrency": "USD",
      "cik": "0001045810",
      "fillingDate": "2019-08-15",
      "acceptedDate": "2019-08-15 17:20:59",
      "calendarYear": "2020",
      "period": "Q2",
      "netIncome": 553000000,
      "depreciationAndAmortization": 92000000,
      "deferredIncomeTax": 15000000,
      "stockBasedCompensation": 223000000,
      "changeInWorkingCapital": 50000000,
      "accountsReceivables": -319000000,
      "inventory": 225000000,
      "accountsPayables": 78000000,
      "otherWorkingCapital": 66000000,
      "otherNonCashItems": 3000000,
      "netCashProvidedByOperatingActivities": 936000000,
      "investmentsInPropertyPlantAndEquipment": -113000000,
      "acquisitionsNet": 0,
      "purchasesOfInvestments": -841000000,
      "salesMaturitiesOfInvestments": 4499000000,
      "otherInvestingActivites": 0,
      "netCashUsedForInvestingActivites": 3545000000,
      "debtRepayment": 0,
      "commonStockIssued": 0,
      "commonStockRepurchased": 0,
      "dividendsPaid": -98000000,
      "otherFinancingActivites": 0,
      "netCashUsedProvidedByFinancingActivities": -148000000,
      "effectOfForexChangesOnCash": 0,
      "netChangeInCash": 4333000000,
      "cashAtEndOfPeriod": 7105000000,
      "cashAtBeginningOfPeriod": 2772000000,
      "operatingCashFlow": 936000000,
      "capitalExpenditure": -113000000,
      "freeCashFlow": 823000000,
      "link": "https://www.sec.gov/Archives/edgar/data/1045810/000104581019000144/0001045810-19-000144-index.htm",
      "finalLink": "https://www.sec.gov/Archives/edgar/data/1045810/000104581019000144/nvda2020q210q.htm"
    },
    {
      "date": "2019-04-28",
      "symbol": "NVDA",
      "reportedCurrency": "USD",
      "cik": "0001045810",
      "fillingDate": "2019-05-16",
      "acceptedDate": "2019-05-16 16:36:34",
      "calendarYear": "2020",
      "period": "Q1",
      "netIncome": 394000000,
      "depreciationAndAmortization": 91000000,
      "deferredIncomeTax": -42000000,
      "stockBasedCompensation": 178000000,
      "changeInWorkingCapital": 101000000,
      "accountsReceivables": 182000000,
      "inventory": 153000000,
      "accountsPayables": -123000000,
      "otherWorkingCapital": -111000000,
      "otherNonCashItems": -2000000,
      "netCashProvidedByOperatingActivities": 720000000,
      "investmentsInPropertyPlantAndEquipment": -128000000,
      "acquisitionsNet": 0,
      "purchasesOfInvestments": -622000000,
      "salesMaturitiesOfInvestments": 2245000000,
      "otherInvestingActivites": 0,
      "netCashUsedForInvestingActivites": 1495000000,
      "debtRepayment": 0,
      "commonStockIssued": 83000000,
      "commonStockRepurchased": 0,
      "dividendsPaid": -97000000,
      "otherFinancingActivites": -211000000,
      "netCashUsedProvidedByFinancingActivities": -225000000,
      "effectOfForexChangesOnCash": 0,
      "netChangeInCash": 1990000000,
      "cashAtEndOfPeriod": 2772000000,
      "cashAtBeginningOfPeriod": 782000000,
      "operatingCashFlow": 720000000,
      "capitalExpenditure": -128000000,
      "freeCashFlow": 592000000,
      "link": "https://www.sec.gov/Archives/edgar/data/1045810/000104581019000079/0001045810-19-000079-index.htm",
      "finalLink": "https://www.sec.gov/Archives/edgar/data/1045810/000104581019000079/nvda2020q110q.htm"
    },
    {
      "date": "2019-01-27",
      "symbol": "NVDA",
      "reportedCurrency": "USD",
      "cik": "0001045810",
      "fillingDate": "2019-02-21",
      "acceptedDate": "2019-02-21 16:37:18",
      "calendarYear": "2019",
      "period": "Q4",
      "netIncome": 566000000,
      "depreciationAndAmortization": 78000000,
      "deferredIncomeTax": -345000000,
      "stockBasedCompensation": 157000000,
      "changeInWorkingCapital": 452000000,
      "accountsReceivables": 794000000,
      "inventory": -156000000,
      "accountsPayables": -359000000,
      "otherWorkingCapital": 173000000,
      "otherNonCashItems": -10000000,
      "netCashProvidedByOperatingActivities": 898000000,
      "investmentsInPropertyPlantAndEquipment": -203000000,
      "acquisitionsNet": 0,
      "purchasesOfInvestments": -1036000000,
      "salesMaturitiesOfInvestments": 1279000000,
      "otherInvestingActivites": 0,
      "netCashUsedForInvestingActivites": 40000000,
      "debtRepayment": -4000000,
      "commonStockIssued": 0,
      "commonStockRepurchased": -724000000,
      "dividendsPaid": -98000000,
      "otherFinancingActivites": -51000000,
      "netCashUsedProvidedByFinancingActivities": -877000000,
      "effectOfForexChangesOnCash": 0,
      "netChangeInCash": 61000000,
      "cashAtEndOfPeriod": 782000000,
      "cashAtBeginningOfPeriod": 721000000,
      "operatingCashFlow": 898000000,
      "capitalExpenditure": -203000000,
      "freeCashFlow": 695000000,
      "link": "https://www.sec.gov/Archives/edgar/data/1045810/000104581019000023/0001045810-19-000023-index.htm",
      "finalLink": "https://www.sec.gov/Archives/edgar/data/1045810/000104581019000023/nvda-2019x10k.htm"
    },
    {
      "date": "2018-10-28",
      "symbol": "NVDA",
      "reportedCurrency": "USD",
      "cik": "0001045810",
      "fillingDate": "2018-11-15",
      "acceptedDate": "2018-11-15 16:32:23",
      "calendarYear": "2019",
      "period": "Q3",
      "netIncome": 1230000000,
      "depreciationAndAmortization": 68000000,
      "deferredIncomeTax": -83000000,
      "stockBasedCompensation": 138000000,
      "changeInWorkingCapital": -853000000,
      "accountsReceivables": -557000000,
      "inventory": -325000000,
      "accountsPayables": 52000000,
      "otherWorkingCapital": -23000000,
      "otherNonCashItems": -13000000,
      "netCashProvidedByOperatingActivities": 487000000,
      "investmentsInPropertyPlantAndEquipment": -150000000,
      "acquisitionsNet": 0,
      "purchasesOfInvestments": -2978000000,
      "salesMaturitiesOfInvestments": 3347000000,
      "otherInvestingActivites": 0,
      "netCashUsedForInvestingActivites": 219000000,
      "debtRepayment": -10000000,
      "commonStockIssued": 0,
      "commonStockRepurchased": -200000000,
      "dividendsPaid": -91000000,
      "otherFinancingActivites": -402000000,
      "netCashUsedProvidedByFinancingActivities": -703000000,
      "effectOfForexChangesOnCash": 0,
      "netChangeInCash": 3000000,
      "cashAtEndOfPeriod": 721000000,
      "cashAtBeginningOfPeriod": 718000000,
      "operatingCashFlow": 487000000,
      "capitalExpenditure": -150000000,
      "freeCashFlow": 337000000,
      "link": "https://www.sec.gov/Archives/edgar/data/1045810/000104581018000150/0001045810-18-000150-index.htm",
      "finalLink": "https://www.sec.gov/Archives/edgar/data/1045810/000104581018000150/nvda2019q310q.htm"
    },
    {
      "date": "2018-07-29",
      "symbol": "NVDA",
      "reportedCurrency": "USD",
      "cik": "0001045810",
      "fillingDate": "2018-08-16",
      "acceptedDate": "2018-08-16 16:31:19",
      "calendarYear": "2019",
      "period": "Q2",
      "netIncome": 1101000000,
      "depreciationAndAmortization": 59000000,
      "deferredIncomeTax": 62000000,
      "stockBasedCompensation": 133000000,
      "changeInWorkingCapital": -428000000,
      "accountsReceivables": -442000000,
      "inventory": -293000000,
      "accountsPayables": 150000000,
      "otherWorkingCapital": 157000000,
      "otherNonCashItems": -14000000,
      "netCashProvidedByOperatingActivities": 913000000,
      "investmentsInPropertyPlantAndEquipment": -129000000,
      "acquisitionsNet": 0,
      "purchasesOfInvestments": -3438000000,
      "salesMaturitiesOfInvestments": 2762000000,
      "otherInvestingActivites": 0,
      "netCashUsedForInvestingActivites": -805000000,
      "debtRepayment": 0,
      "commonStockIssued": 3000000,
      "commonStockRepurchased": 0,
      "dividendsPaid": -91000000,
      "otherFinancingActivites": -67000000,
      "netCashUsedProvidedByFinancingActivities": -155000000,
      "effectOfForexChangesOnCash": 0,
      "netChangeInCash": -47000000,
      "cashAtEndOfPeriod": 718000000,
      "cashAtBeginningOfPeriod": 765000000,
      "operatingCashFlow": 913000000,
      "capitalExpenditure": -129000000,
      "freeCashFlow": 784000000,
      "link": "https://www.sec.gov/Archives/edgar/data/1045810/000104581018000114/0001045810-18-000114-index.htm",
      "finalLink": "https://www.sec.gov/Archives/edgar/data/1045810/000104581018000114/nvda2019q210q.htm"
    },
    {
      "date": "2018-04-29",
      "symbol": "NVDA",
      "reportedCurrency": "USD",
      "cik": "0001045810",
      "fillingDate": "2018-05-22",
      "acceptedDate": "2018-05-22 16:35:51",
      "calendarYear": "2019",
      "period": "Q1",
      "netIncome": 1244000000,
      "depreciationAndAmortization": 57000000,
      "deferredIncomeTax": 51000000,
      "stockBasedCompensation": 129000000,
      "changeInWorkingCapital": -28000000,
      "accountsReceivables": 56000000,
      "inventory": -2000000,
      "accountsPayables": 22000000,
      "otherWorkingCapital": -104000000,
      "otherNonCashItems": -8000000,
      "netCashProvidedByOperatingActivities": 1445000000,
      "investmentsInPropertyPlantAndEquipment": -118000000,
      "acquisitionsNet": 0,
      "purchasesOfInvestments": -3705000000,
      "salesMaturitiesOfInvestments": 272000000,
      "otherInvestingActivites": 0,
      "netCashUsedForInvestingActivites": -3551000000,
      "debtRepayment": -2000000,
      "commonStockIssued": 0,
      "commonStockRepurchased": -655000000,
      "dividendsPaid": -91000000,
      "otherFinancingActivites": -383000000,
      "netCashUsedProvidedByFinancingActivities": -1131000000,
      "effectOfForexChangesOnCash": 0,
      "netChangeInCash": -3237000000,
      "cashAtEndOfPeriod": 765000000,
      "cashAtBeginningOfPeriod": 4002000000,
      "operatingCashFlow": 1445000000,
      "capitalExpenditure": -118000000,
      "freeCashFlow": 1327000000,
      "link": "https://www.sec.gov/Archives/edgar/data/1045810/000104581018000080/0001045810-18-000080-index.htm",
      "finalLink": "https://www.sec.gov/Archives/edgar/data/1045810/000104581018000080/nvda2019q110q.htm"
    },
    {
      "date": "2018-01-28",
      "symbol": "NVDA",
      "reportedCurrency": "USD",
      "cik": "0001045810",
      "fillingDate": "2018-02-28",
      "acceptedDate": "2018-02-28 16:31:19",
      "calendarYear": "2018",
      "period": "Q4",
      "netIncome": 1119000000,
      "depreciationAndAmortization": 54000000,
      "deferredIncomeTax": -517000000,
      "stockBasedCompensation": 126000000,
      "changeInWorkingCapital": 571000000,
      "accountsReceivables": -98000000,
      "inventory": 61000000,
      "accountsPayables": 63000000,
      "otherWorkingCapital": 545000000,
      "otherNonCashItems": 5000000,
      "netCashProvidedByOperatingActivities": 1358000000,
      "investmentsInPropertyPlantAndEquipment": -416000000,
      "acquisitionsNet": 0,
      "purchasesOfInvestments": -10000000,
      "salesMaturitiesOfInvestments": 400000000,
      "otherInvestingActivites": 2000000,
      "netCashUsedForInvestingActivites": -24000000,
      "debtRepayment": -9000000,
      "commonStockIssued": 7000000,
      "commonStockRepurchased": 0,
      "dividendsPaid": -91000000,
      "otherFinancingActivites": -41000000,
      "netCashUsedProvidedByFinancingActivities": -134000000,
      "effectOfForexChangesOnCash": 0,
      "netChangeInCash": 1200000000,
      "cashAtEndOfPeriod": 4002000000,
      "cashAtBeginningOfPeriod": 2802000000,
      "operatingCashFlow": 1358000000,
      "capitalExpenditure": -416000000,
      "freeCashFlow": 942000000,
      "link": "https://www.sec.gov/Archives/edgar/data/1045810/000104581018000010/0001045810-18-000010-index.htm",
      "finalLink": "https://www.sec.gov/Archives/edgar/data/1045810/000104581018000010/nvda-2018x10k.htm"
    },
    {
      "date": "2017-10-29",
      "symbol": "NVDA",
      "reportedCurrency": "USD",
      "cik": "0001045810",
      "fillingDate": "2017-11-21",
      "acceptedDate": "2017-11-21 16:25:20",
      "calendarYear": "2018",
      "period": "Q3",
      "netIncome": 837000000,
      "depreciationAndAmortization": 49000000,
      "deferredIncomeTax": 43000000,
      "stockBasedCompensation": 107000000,
      "changeInWorkingCapital": 115000000,
      "accountsReceivables": 45000000,
      "inventory": 0,
      "accountsPayables": 90000000,
      "otherWorkingCapital": -20000000,
      "otherNonCashItems": 6000000,
      "netCashProvidedByOperatingActivities": 1157000000,
      "investmentsInPropertyPlantAndEquipment": -69000000,
      "acquisitionsNet": 0,
      "purchasesOfInvestments": -10000000,
      "salesMaturitiesOfInvestments": 365000000,
      "otherInvestingActivites": 0,
      "netCashUsedForInvestingActivites": 286000000,
      "debtRepayment": -62000000,
      "commonStockIssued": 0,
      "commonStockRepurchased": -151000000,
      "dividendsPaid": -84000000,
      "otherFinancingActivites": -332000000,
      "netCashUsedProvidedByFinancingActivities": -629000000,
      "effectOfForexChangesOnCash": 0,
      "netChangeInCash": 814000000,
      "cashAtEndOfPeriod": 2802000000,
      "cashAtBeginningOfPeriod": 1988000000,
      "operatingCashFlow": 1157000000,
      "capitalExpenditure": -69000000,
      "freeCashFlow": 1088000000,
      "link": "https://www.sec.gov/Archives/edgar/data/1045810/000104581017000172/0001045810-17-000172-index.htm",
      "finalLink": "https://www.sec.gov/Archives/edgar/data/1045810/000104581017000172/nvda2018q310q.htm"
    },
    {
      "date": "2017-07-30",
      "symbol": "NVDA",
      "reportedCurrency": "USD",
      "cik": "0001045810",
      "fillingDate": "2017-08-23",
      "acceptedDate": "2017-08-23 16:24:51",
      "calendarYear": "2018",
      "period": "Q2",
      "netIncome": 584000000,
      "depreciationAndAmortization": 49000000,
      "deferredIncomeTax": 93000000,
      "stockBasedCompensation": 82000000,
      "changeInWorkingCapital": -110000000,
      "accountsReceivables": -237000000,
      "inventory": -34000000,
      "accountsPayables": 70000000,
      "otherWorkingCapital": 91000000,
      "otherNonCashItems": 7000000,
      "netCashProvidedByOperatingActivities": 705000000,
      "investmentsInPropertyPlantAndEquipment": -54000000,
      "acquisitionsNet": 0,
      "purchasesOfInvestments": -11000000,
      "salesMaturitiesOfInvestments": 327000000,
      "otherInvestingActivites": 0,
      "netCashUsedForInvestingActivites": 262000000,
      "debtRepayment": -136000000,
      "commonStockIssued": 0,
      "commonStockRepurchased": -758000000,
      "dividendsPaid": -84000000,
      "otherFinancingActivites": 10000000,
      "netCashUsedProvidedByFinancingActivities": -968000000,
      "effectOfForexChangesOnCash": 0,
      "netChangeInCash": -1000000,
      "cashAtEndOfPeriod": 1988000000,
      "cashAtBeginningOfPeriod": 1989000000,
      "operatingCashFlow": 705000000,
      "capitalExpenditure": -54000000,
      "freeCashFlow": 651000000,
      "link": "https://www.sec.gov/Archives/edgar/data/1045810/000104581017000123/0001045810-17-000123-index.htm",
      "finalLink": "https://www.sec.gov/Archives/edgar/data/1045810/000104581017000123/nvda2018q210q.htm"
    },
    {
      "date": "2017-04-30",
      "symbol": "NVDA",
      "reportedCurrency": "USD",
      "cik": "0001045810",
      "fillingDate": "2017-05-23",
      "acceptedDate": "2017-05-23 16:34:55",
      "calendarYear": "2018",
      "period": "Q1",
      "netIncome": 507000000,
      "depreciationAndAmortization": 47000000,
      "deferredIncomeTax": 22000000,
      "stockBasedCompensation": 76000000,
      "changeInWorkingCapital": -391000000,
      "accountsReceivables": -150000000,
      "inventory": -27000000,
      "accountsPayables": -133000000,
      "otherWorkingCapital": -81000000,
      "otherNonCashItems": 21000000,
      "netCashProvidedByOperatingActivities": 282000000,
      "investmentsInPropertyPlantAndEquipment": -54000000,
      "acquisitionsNet": 0,
      "purchasesOfInvestments": -41000000,
      "salesMaturitiesOfInvestments": 849000000,
      "otherInvestingActivites": 0,
      "netCashUsedForInvestingActivites": 754000000,
      "debtRepayment": -605000000,
      "commonStockIssued": 0,
      "commonStockRepurchased": -190000000,
      "dividendsPaid": -82000000,
      "otherFinancingActivites": 64000000,
      "netCashUsedProvidedByFinancingActivities": -813000000,
      "effectOfForexChangesOnCash": 0,
      "netChangeInCash": 223000000,
      "cashAtEndOfPeriod": 1989000000,
      "cashAtBeginningOfPeriod": 1766000000,
      "operatingCashFlow": 282000000,
      "capitalExpenditure": -54000000,
      "freeCashFlow": 228000000,
      "link": "https://www.sec.gov/Archives/edgar/data/1045810/000104581017000075/0001045810-17-000075-index.htm",
      "finalLink": "https://www.sec.gov/Archives/edgar/data/1045810/000104581017000075/nvda2018q110q.htm"
    },
    {
      "date": "2017-01-29",
      "symbol": "NVDA",
      "reportedCurrency": "USD",
      "cik": "0001045810",
      "fillingDate": "2017-03-01",
      "acceptedDate": "2017-03-01 17:30:49",
      "calendarYear": "2017",
      "period": "Q4",
      "netIncome": 654000000,
      "depreciationAndAmortization": 47000000,
      "deferredIncomeTax": 51000000,
      "stockBasedCompensation": 71000000,
      "changeInWorkingCapital": -115000000,
      "accountsReceivables": 7000000,
      "inventory": -114000000,
      "accountsPayables": -34000000,
      "otherWorkingCapital": 26000000,
      "otherNonCashItems": 13000000,
      "netCashProvidedByOperatingActivities": 721000000,
      "investmentsInPropertyPlantAndEquipment": -51000000,
      "acquisitionsNet": 0,
      "purchasesOfInvestments": -885000000,
      "salesMaturitiesOfInvestments": 564000000,
      "otherInvestingActivites": -1000000,
      "netCashUsedForInvestingActivites": -373000000,
      "debtRepayment": -226000000,
      "commonStockIssued": 0,
      "commonStockRepurchased": -230000000,
      "dividendsPaid": -76000000,
      "otherFinancingActivites": 10000000,
      "netCashUsedProvidedByFinancingActivities": -522000000,
      "effectOfForexChangesOnCash": 0,
      "netChangeInCash": -174000000,
      "cashAtEndOfPeriod": 1766000000,
      "cashAtBeginningOfPeriod": 1940000000,
      "operatingCashFlow": 721000000,
      "capitalExpenditure": -51000000,
      "freeCashFlow": 670000000,
      "link": "https://www.sec.gov/Archives/edgar/data/1045810/000104581017000027/0001045810-17-000027-index.htm",
      "finalLink": "https://www.sec.gov/Archives/edgar/data/1045810/000104581017000027/nvda-2017x10k.htm"
    },
    {
      "date": "2016-10-30",
      "symbol": "NVDA",
      "reportedCurrency": "USD",
      "cik": "0001045810",
      "fillingDate": "2016-11-22",
      "acceptedDate": "2016-11-22 16:29:33",
      "calendarYear": "2017",
      "period": "Q3",
      "netIncome": 543000000,
      "depreciationAndAmortization": 48000000,
      "deferredIncomeTax": 69000000,
      "stockBasedCompensation": 65000000,
      "changeInWorkingCapital": -316000000,
      "accountsReceivables": -190000000,
      "inventory": -157000000,
      "accountsPayables": 87000000,
      "otherWorkingCapital": -56000000,
      "otherNonCashItems": 23000000,
      "netCashProvidedByOperatingActivities": 432000000,
      "investmentsInPropertyPlantAndEquipment": -38000000,
      "acquisitionsNet": 0,
      "purchasesOfInvestments": -833000000,
      "salesMaturitiesOfInvestments": 544000000,
      "otherInvestingActivites": 0,
      "netCashUsedForInvestingActivites": -327000000,
      "debtRepayment": 1544000000,
      "commonStockIssued": 0,
      "commonStockRepurchased": -126000000,
      "dividendsPaid": -61000000,
      "otherFinancingActivites": 52000000,
      "netCashUsedProvidedByFinancingActivities": 1409000000,
      "effectOfForexChangesOnCash": 0,
      "netChangeInCash": 1514000000,
      "cashAtEndOfPeriod": 1940000000,
      "cashAtBeginningOfPeriod": 426000000,
      "operatingCashFlow": 432000000,
      "capitalExpenditure": -38000000,
      "freeCashFlow": 394000000,
      "link": "https://www.sec.gov/Archives/edgar/data/1045810/000104581016000353/0001045810-16-000353-index.htm",
      "finalLink": "https://www.sec.gov/Archives/edgar/data/1045810/000104581016000353/nvda2017q310q.htm"
    },
    {
      "date": "2016-07-31",
      "symbol": "NVDA",
      "reportedCurrency": "USD",
      "cik": "0001045810",
      "fillingDate": "2016-08-23",
      "acceptedDate": "2016-08-23 17:20:18",
      "calendarYear": "2017",
      "period": "Q2",
      "netIncome": 261000000,
      "depreciationAndAmortization": 47000000,
      "deferredIncomeTax": 47000000,
      "stockBasedCompensation": 58000000,
      "changeInWorkingCapital": -230000000,
      "accountsReceivables": -121000000,
      "inventory": -127000000,
      "accountsPayables": 99000000,
      "otherWorkingCapital": -81000000,
      "otherNonCashItems": 17000000,
      "netCashProvidedByOperatingActivities": 200000000,
      "investmentsInPropertyPlantAndEquipment": -32000000,
      "acquisitionsNet": 0,
      "purchasesOfInvestments": -946000000,
      "salesMaturitiesOfInvestments": 703000000,
      "otherInvestingActivites": 6000000,
      "netCashUsedForInvestingActivites": -269000000,
      "debtRepayment": 0,
      "commonStockIssued": 0,
      "commonStockRepurchased": -9000000,
      "dividendsPaid": -62000000,
      "otherFinancingActivites": 19000000,
      "netCashUsedProvidedByFinancingActivities": -52000000,
      "effectOfForexChangesOnCash": 0,
      "netChangeInCash": -121000000,
      "cashAtEndOfPeriod": 426000000,
      "cashAtBeginningOfPeriod": 547000000,
      "operatingCashFlow": 200000000,
      "capitalExpenditure": -32000000,
      "freeCashFlow": 168000000,
      "link": "https://www.sec.gov/Archives/edgar/data/1045810/000104581016000300/0001045810-16-000300-index.htm",
      "finalLink": "https://www.sec.gov/Archives/edgar/data/1045810/000104581016000300/nvda2017q210q.htm"
    },
    {
      "date": "2016-05-01",
      "symbol": "NVDA",
      "reportedCurrency": "USD",
      "cik": "0001045810",
      "fillingDate": "2016-05-25",
      "acceptedDate": "2016-05-25 16:55:13",
      "calendarYear": "2017",
      "period": "Q1",
      "netIncome": 208000000,
      "depreciationAndAmortization": 45000000,
      "deferredIncomeTax": 30000000,
      "stockBasedCompensation": 53000000,
      "changeInWorkingCapital": -18000000,
      "accountsReceivables": -17000000,
      "inventory": 23000000,
      "accountsPayables": 32000000,
      "otherWorkingCapital": -56000000,
      "otherNonCashItems": 1000000,
      "netCashProvidedByOperatingActivities": 319000000,
      "investmentsInPropertyPlantAndEquipment": -55000000,
      "acquisitionsNet": 0,
      "purchasesOfInvestments": -473000000,
      "salesMaturitiesOfInvestments": 704000000,
      "otherInvestingActivites": 0,
      "netCashUsedForInvestingActivites": 176000000,
      "debtRepayment": 0,
      "commonStockIssued": 0,
      "commonStockRepurchased": -500000000,
      "dividendsPaid": -62000000,
      "otherFinancingActivites": 18000000,
      "netCashUsedProvidedByFinancingActivities": -544000000,
      "effectOfForexChangesOnCash": 0,
      "netChangeInCash": -49000000,
      "cashAtEndOfPeriod": 547000000,
      "cashAtBeginningOfPeriod": 596000000,
      "operatingCashFlow": 319000000,
      "capitalExpenditure": -55000000,
      "freeCashFlow": 264000000,
      "link": "https://www.sec.gov/Archives/edgar/data/1045810/000104581016000275/0001045810-16-000275-index.htm",
      "finalLink": "https://www.sec.gov/Archives/edgar/data/1045810/000104581016000275/nvda2017q110q.htm"
    },
    {
      "date": "2016-01-31",
      "symbol": "NVDA",
      "reportedCurrency": "USD",
      "cik": "0001045810",
      "fillingDate": "2016-03-17",
      "acceptedDate": "2016-03-16 18:07:18",
      "calendarYear": "2016",
      "period": "Q4",
      "netIncome": 208000000,
      "depreciationAndAmortization": 46000000,
      "deferredIncomeTax": 27000000,
      "stockBasedCompensation": 59000000,
      "changeInWorkingCapital": 157000000,
      "accountsReceivables": 31000000,
      "inventory": 7000000,
      "accountsPayables": -18000000,
      "otherWorkingCapital": 137000000,
      "otherNonCashItems": 14000000,
      "netCashProvidedByOperatingActivities": 511000000,
      "investmentsInPropertyPlantAndEquipment": -15000000,
      "acquisitionsNet": 0,
      "purchasesOfInvestments": -808000000,
      "salesMaturitiesOfInvestments": 615000000,
      "otherInvestingActivites": -5000000,
      "netCashUsedForInvestingActivites": -213000000,
      "debtRepayment": 0,
      "commonStockIssued": 0,
      "commonStockRepurchased": -135000000,
      "dividendsPaid": -61000000,
      "otherFinancingActivites": 23000000,
      "netCashUsedProvidedByFinancingActivities": -173000000,
      "effectOfForexChangesOnCash": 0,
      "netChangeInCash": 125000000,
      "cashAtEndOfPeriod": 596000000,
      "cashAtBeginningOfPeriod": 471000000,
      "operatingCashFlow": 511000000,
      "capitalExpenditure": -15000000,
      "freeCashFlow": 496000000,
      "link": "https://www.sec.gov/Archives/edgar/data/1045810/000104581016000205/0001045810-16-000205-index.htm",
      "finalLink": "https://www.sec.gov/Archives/edgar/data/1045810/000104581016000205/nvda-2016x10k.htm"
    },
    {
      "date": "2015-10-25",
      "symbol": "NVDA",
      "reportedCurrency": "USD",
      "cik": "0001045810",
      "fillingDate": "2015-11-18",
      "acceptedDate": "2015-11-18 16:39:57",
      "calendarYear": "2016",
      "period": "Q3",
      "netIncome": 246000000,
      "depreciationAndAmortization": 48000000,
      "deferredIncomeTax": 42000000,
      "stockBasedCompensation": 52000000,
      "changeInWorkingCapital": -148000000,
      "accountsReceivables": -22000000,
      "inventory": 17000000,
      "accountsPayables": 20000000,
      "otherWorkingCapital": -163000000,
      "otherNonCashItems": 15000000,
      "netCashProvidedByOperatingActivities": 255000000,
      "investmentsInPropertyPlantAndEquipment": -17000000,
      "acquisitionsNet": 0,
      "purchasesOfInvestments": -808000000,
      "salesMaturitiesOfInvestments": 621000000,
      "otherInvestingActivites": 5000000,
      "netCashUsedForInvestingActivites": -199000000,
      "debtRepayment": -1000000,
      "commonStockIssued": 0,
      "commonStockRepurchased": 0,
      "dividendsPaid": -53000000,
      "otherFinancingActivites": 34000000,
      "netCashUsedProvidedByFinancingActivities": -20000000,
      "effectOfForexChangesOnCash": 0,
      "netChangeInCash": 36000000,
      "cashAtEndOfPeriod": 471000000,
      "cashAtBeginningOfPeriod": 435000000,
      "operatingCashFlow": 255000000,
      "capitalExpenditure": -17000000,
      "freeCashFlow": 238000000,
      "link": "https://www.sec.gov/Archives/edgar/data/1045810/000104581015000173/0001045810-15-000173-index.htm",
      "finalLink": "https://www.sec.gov/Archives/edgar/data/1045810/000104581015000173/nvda2016q310q.htm"
    },
    {
      "date": "2015-07-26",
      "symbol": "NVDA",
      "reportedCurrency": "USD",
      "cik": "0001045810",
      "fillingDate": "2015-08-19",
      "acceptedDate": "2015-08-19 16:41:18",
      "calendarYear": "2016",
      "period": "Q2",
      "netIncome": 26000000,
      "depreciationAndAmortization": 49000000,
      "deferredIncomeTax": 37000000,
      "stockBasedCompensation": 48000000,
      "changeInWorkingCapital": -40000000,
      "accountsReceivables": -59000000,
      "inventory": -3000000,
      "accountsPayables": 54000000,
      "otherWorkingCapital": -32000000,
      "otherNonCashItems": 43000000,
      "netCashProvidedByOperatingActivities": 163000000,
      "investmentsInPropertyPlantAndEquipment": -24000000,
      "acquisitionsNet": 0,
      "purchasesOfInvestments": -594000000,
      "salesMaturitiesOfInvestments": 839000000,
      "otherInvestingActivites": 26000000,
      "netCashUsedForInvestingActivites": 247000000,
      "debtRepayment": -1000000,
      "commonStockIssued": 0,
      "commonStockRepurchased": -399000000,
      "dividendsPaid": -53000000,
      "otherFinancingActivites": 14000000,
      "netCashUsedProvidedByFinancingActivities": -439000000,
      "effectOfForexChangesOnCash": 0,
      "netChangeInCash": -29000000,
      "cashAtEndOfPeriod": 435000000,
      "cashAtBeginningOfPeriod": 464000000,
      "operatingCashFlow": 163000000,
      "capitalExpenditure": -24000000,
      "freeCashFlow": 139000000,
      "link": "https://www.sec.gov/Archives/edgar/data/1045810/000104581015000143/0001045810-15-000143-index.htm",
      "finalLink": "https://www.sec.gov/Archives/edgar/data/1045810/000104581015000143/nvda2016q210q.htm"
    },
    {
      "date": "2015-04-26",
      "symbol": "NVDA",
      "reportedCurrency": "USD",
      "cik": "0001045810",
      "fillingDate": "2015-05-20",
      "acceptedDate": "2015-05-20 16:55:12",
      "calendarYear": "2016",
      "period": "Q1",
      "netIncome": 134000000,
      "depreciationAndAmortization": 54000000,
      "deferredIncomeTax": 28000000,
      "stockBasedCompensation": 45000000,
      "changeInWorkingCapital": -20000000,
      "accountsReceivables": 18000000,
      "inventory": 45000000,
      "accountsPayables": -67000000,
      "otherWorkingCapital": -16000000,
      "otherNonCashItems": 5000000,
      "netCashProvidedByOperatingActivities": 246000000,
      "investmentsInPropertyPlantAndEquipment": -30000000,
      "acquisitionsNet": 0,
      "purchasesOfInvestments": -1267000000,
      "salesMaturitiesOfInvestments": 1063000000,
      "otherInvestingActivites": -1000000,
      "netCashUsedForInvestingActivites": -235000000,
      "debtRepayment": -1000000,
      "commonStockIssued": 0,
      "commonStockRepurchased": -53000000,
      "dividendsPaid": -46000000,
      "otherFinancingActivites": 56000000,
      "netCashUsedProvidedByFinancingActivities": -44000000,
      "effectOfForexChangesOnCash": 0,
      "netChangeInCash": -33000000,
      "cashAtEndOfPeriod": 464000000,
      "cashAtBeginningOfPeriod": 497000000,
      "operatingCashFlow": 246000000,
      "capitalExpenditure": -30000000,
      "freeCashFlow": 216000000,
      "link": "https://www.sec.gov/Archives/edgar/data/1045810/000104581015000097/0001045810-15-000097-index.htm",
      "finalLink": "https://www.sec.gov/Archives/edgar/data/1045810/000104581015000097/nvda2016q110q.htm"
    },
    {
      "date": "2015-01-25",
      "symbol": "NVDA",
      "reportedCurrency": "USD",
      "cik": "0001045810",
      "fillingDate": "2015-03-12",
      "acceptedDate": "2015-03-11 19:48:05",
      "calendarYear": "2015",
      "period": "Q4",
      "netIncome": 193128000,
      "depreciationAndAmortization": 53955000,
      "deferredIncomeTax": 20488000,
      "stockBasedCompensation": 42470000,
      "changeInWorkingCapital": 126456000,
      "accountsReceivables": 89405000,
      "inventory": -75109000,
      "accountsPayables": -36722000,
      "otherWorkingCapital": 148882000,
      "otherNonCashItems": 6232000,
      "netCashProvidedByOperatingActivities": 442729000,
      "investmentsInPropertyPlantAndEquipment": -31045000,
      "acquisitionsNet": 0,
      "purchasesOfInvestments": -735730000,
      "salesMaturitiesOfInvestments": 448598000,
      "otherInvestingActivites": 0,
      "netCashUsedForInvestingActivites": -318177000,
      "debtRepayment": -757000,
      "commonStockIssued": 0,
      "commonStockRepurchased": -3600000,
      "dividendsPaid": -46217000,
      "otherFinancingActivites": 27993000,
      "netCashUsedProvidedByFinancingActivities": -22581000,
      "effectOfForexChangesOnCash": 0,
      "netChangeInCash": 101971000,
      "cashAtEndOfPeriod": 496654000,
      "cashAtBeginningOfPeriod": 394683000,
      "operatingCashFlow": 442729000,
      "capitalExpenditure": -31045000,
      "freeCashFlow": 411684000,
      "link": "https://www.sec.gov/Archives/edgar/data/1045810/000104581015000036/0001045810-15-000036-index.htm",
      "finalLink": "https://www.sec.gov/Archives/edgar/data/1045810/000104581015000036/nvda-2015x10k.htm"
    },
    {
      "date": "2014-10-26",
      "symbol": "NVDA",
      "reportedCurrency": "USD",
      "cik": "0001045810",
      "fillingDate": "2014-11-19",
      "acceptedDate": "2014-11-18 19:09:07",
      "calendarYear": "2015",
      "period": "Q3",
      "netIncome": 172000000,
      "depreciationAndAmortization": 55000000,
      "deferredIncomeTax": 24000000,
      "stockBasedCompensation": 41000000,
      "changeInWorkingCapital": -79000000,
      "accountsReceivables": -92000000,
      "inventory": -21000000,
      "accountsPayables": 74000000,
      "otherWorkingCapital": -40000000,
      "otherNonCashItems": 3000000,
      "netCashProvidedByOperatingActivities": 216000000,
      "investmentsInPropertyPlantAndEquipment": -39000000,
      "acquisitionsNet": 0,
      "purchasesOfInvestments": -443000000,
      "salesMaturitiesOfInvestments": 468000000,
      "otherInvestingActivites": -1000000,
      "netCashUsedForInvestingActivites": -15000000,
      "debtRepayment": -1000000,
      "commonStockIssued": 0,
      "commonStockRepurchased": -310000000,
      "dividendsPaid": -46000000,
      "otherFinancingActivites": 36000000,
      "netCashUsedProvidedByFinancingActivities": -321000000,
      "effectOfForexChangesOnCash": 0,
      "netChangeInCash": -120000000,
      "cashAtEndOfPeriod": 395000000,
      "cashAtBeginningOfPeriod": 515000000,
      "operatingCashFlow": 216000000,
      "capitalExpenditure": -39000000,
      "freeCashFlow": 177000000,
      "link": "https://www.sec.gov/Archives/edgar/data/1045810/000104581014000188/0001045810-14-000188-index.htm",
      "finalLink": "https://www.sec.gov/Archives/edgar/data/1045810/000104581014000188/nvda2015q310q.htm"
    },
    {
      "date": "2014-07-27",
      "symbol": "NVDA",
      "reportedCurrency": "USD",
      "cik": "0001045810",
      "fillingDate": "2014-08-20",
      "acceptedDate": "2014-08-20 16:27:59",
      "calendarYear": "2015",
      "period": "Q2",
      "netIncome": 128000000,
      "depreciationAndAmortization": 56000000,
      "deferredIncomeTax": 16000000,
      "stockBasedCompensation": 38000000,
      "changeInWorkingCapital": -156000000,
      "accountsReceivables": -74000000,
      "inventory": 7000000,
      "accountsPayables": -49000000,
      "otherWorkingCapital": -40000000,
      "otherNonCashItems": 14000000,
      "netCashProvidedByOperatingActivities": 96000000,
      "investmentsInPropertyPlantAndEquipment": -23000000,
      "acquisitionsNet": 0,
      "purchasesOfInvestments": -682000000,
      "salesMaturitiesOfInvestments": 641000000,
      "otherInvestingActivites": 0,
      "netCashUsedForInvestingActivites": -64000000,
      "debtRepayment": 0,
      "commonStockIssued": 0,
      "commonStockRepurchased": 0,
      "dividendsPaid": -47000000,
      "otherFinancingActivites": 21000000,
      "netCashUsedProvidedByFinancingActivities": -26000000,
      "effectOfForexChangesOnCash": 0,
      "netChangeInCash": 6000000,
      "cashAtEndOfPeriod": 515000000,
      "cashAtBeginningOfPeriod": 509000000,
      "operatingCashFlow": 96000000,
      "capitalExpenditure": -23000000,
      "freeCashFlow": 73000000,
      "link": "https://www.sec.gov/Archives/edgar/data/1045810/000104581014000158/0001045810-14-000158-index.htm",
      "finalLink": "https://www.sec.gov/Archives/edgar/data/1045810/000104581014000158/nvda2015q210q.htm"
    },
    {
      "date": "2014-04-27",
      "symbol": "NVDA",
      "reportedCurrency": "USD",
      "cik": "0001045810",
      "fillingDate": "2014-05-21",
      "acceptedDate": "2014-05-21 16:11:13",
      "calendarYear": "2015",
      "period": "Q1",
      "netIncome": 137000000,
      "depreciationAndAmortization": 55000000,
      "deferredIncomeTax": 22000000,
      "stockBasedCompensation": 36000000,
      "changeInWorkingCapital": -92000000,
      "accountsReceivables": 28000000,
      "inventory": -6000000,
      "accountsPayables": -15000000,
      "otherWorkingCapital": -99000000,
      "otherNonCashItems": -7000000,
      "netCashProvidedByOperatingActivities": 151000000,
      "investmentsInPropertyPlantAndEquipment": -29000000,
      "acquisitionsNet": 0,
      "purchasesOfInvestments": -1001000000,
      "salesMaturitiesOfInvestments": 679000000,
      "otherInvestingActivites": 21000000,
      "netCashUsedForInvestingActivites": -330000000,
      "debtRepayment": -1000000,
      "commonStockIssued": 0,
      "commonStockRepurchased": -500000000,
      "dividendsPaid": -47000000,
      "otherFinancingActivites": 84000000,
      "netCashUsedProvidedByFinancingActivities": -464000000,
      "effectOfForexChangesOnCash": 0,
      "netChangeInCash": -643000000,
      "cashAtEndOfPeriod": 509000000,
      "cashAtBeginningOfPeriod": 1152000000,
      "operatingCashFlow": 151000000,
      "capitalExpenditure": -29000000,
      "freeCashFlow": 122000000,
      "link": "https://www.sec.gov/Archives/edgar/data/1045810/000104581014000085/0001045810-14-000085-index.htm",
      "finalLink": "https://www.sec.gov/Archives/edgar/data/1045810/000104581014000085/nvda2015q110q.htm"
    },
    {
      "date": "2014-01-26",
      "symbol": "NVDA",
      "reportedCurrency": "USD",
      "cik": "0001045810",
      "fillingDate": "2014-03-13",
      "acceptedDate": "2014-03-12 19:18:57",
      "calendarYear": "2014",
      "period": "Q4",
      "netIncome": 146917000,
      "depreciationAndAmortization": 54838000,
      "deferredIncomeTax": 7516000,
      "stockBasedCompensation": 36204000,
      "changeInWorkingCapital": 150759000,
      "accountsReceivables": 21046000,
      "inventory": -7527000,
      "accountsPayables": 17994000,
      "otherWorkingCapital": 119246000,
      "otherNonCashItems": 4478000,
      "netCashProvidedByOperatingActivities": 400712000,
      "investmentsInPropertyPlantAndEquipment": -66374000,
      "acquisitionsNet": 0,
      "purchasesOfInvestments": -1644933000,
      "salesMaturitiesOfInvestments": 589430000,
      "otherInvestingActivites": 22281000,
      "netCashUsedForInvestingActivites": -1099596000,
      "debtRepayment": 0,
      "commonStockIssued": 0,
      "commonStockRepurchased": -37304000,
      "dividendsPaid": -48329000,
      "otherFinancingActivites": 1374020000,
      "netCashUsedProvidedByFinancingActivities": 1288387000,
      "effectOfForexChangesOnCash": 0,
      "netChangeInCash": 589503000,
      "cashAtEndOfPeriod": 1151587000,
      "cashAtBeginningOfPeriod": 562084000,
      "operatingCashFlow": 400712000,
      "capitalExpenditure": -66374000,
      "freeCashFlow": 334338000,
      "link": "https://www.sec.gov/Archives/edgar/data/1045810/000104581014000030/0001045810-14-000030-index.htm",
      "finalLink": "https://www.sec.gov/Archives/edgar/data/1045810/000104581014000030/nvda-2014x10k.htm"
    },
    {
      "date": "2013-10-27",
      "symbol": "NVDA",
      "reportedCurrency": "USD",
      "cik": "0001045810",
      "fillingDate": "2013-11-19",
      "acceptedDate": "2013-11-19 16:30:37",
      "calendarYear": "2014",
      "period": "Q3",
      "netIncome": 118734000,
      "depreciationAndAmortization": 62726000,
      "deferredIncomeTax": 8525000,
      "stockBasedCompensation": 34299000,
      "changeInWorkingCapital": -58030000,
      "accountsReceivables": -29465000,
      "inventory": -2544000,
      "accountsPayables": -1924000,
      "otherWorkingCapital": -24097000,
      "otherNonCashItems": -3939000,
      "netCashProvidedByOperatingActivities": 162315000,
      "investmentsInPropertyPlantAndEquipment": -38159000,
      "acquisitionsNet": 0,
      "purchasesOfInvestments": -484257000,
      "salesMaturitiesOfInvestments": 353188000,
      "otherInvestingActivites": -18145000,
      "netCashUsedForInvestingActivites": -187373000,
      "debtRepayment": -611000,
      "commonStockIssued": 0,
      "commonStockRepurchased": 0,
      "dividendsPaid": -43397000,
      "otherFinancingActivites": 39829000,
      "netCashUsedProvidedByFinancingActivities": -4179000,
      "effectOfForexChangesOnCash": 0,
      "netChangeInCash": -29237000,
      "cashAtEndOfPeriod": 562084000,
      "cashAtBeginningOfPeriod": 591321000,
      "operatingCashFlow": 162315000,
      "capitalExpenditure": -38159000,
      "freeCashFlow": 124156000,
      "link": "https://www.sec.gov/Archives/edgar/data/1045810/000104581013000109/0001045810-13-000109-index.htm",
      "finalLink": "https://www.sec.gov/Archives/edgar/data/1045810/000104581013000109/nvda2014q310q.htm"
    },
    {
      "date": "2013-07-28",
      "symbol": "NVDA",
      "reportedCurrency": "USD",
      "cik": "0001045810",
      "fillingDate": "2013-08-21",
      "acceptedDate": "2013-08-21 16:25:58",
      "calendarYear": "2014",
      "period": "Q2",
      "netIncome": 96448000,
      "depreciationAndAmortization": 61840000,
      "deferredIncomeTax": 2452000,
      "stockBasedCompensation": 32395000,
      "changeInWorkingCapital": -93305000,
      "accountsReceivables": -71205000,
      "inventory": -6788000,
      "accountsPayables": 16649000,
      "otherWorkingCapital": -31961000,
      "otherNonCashItems": -3361000,
      "netCashProvidedByOperatingActivities": 96469000,
      "investmentsInPropertyPlantAndEquipment": -84986000,
      "acquisitionsNet": 0,
      "purchasesOfInvestments": -394264000,
      "salesMaturitiesOfInvestments": 1191068000,
      "otherInvestingActivites": 0,
      "netCashUsedForInvestingActivites": 711818000,
      "debtRepayment": -593000,
      "commonStockIssued": 0,
      "commonStockRepurchased": -750000000,
      "dividendsPaid": -43343000,
      "otherFinancingActivites": 15547000,
      "netCashUsedProvidedByFinancingActivities": -778389000,
      "effectOfForexChangesOnCash": 0,
      "netChangeInCash": 29898000,
      "cashAtEndOfPeriod": 591321000,
      "cashAtBeginningOfPeriod": 561423000,
      "operatingCashFlow": 96469000,
      "capitalExpenditure": -84986000,
      "freeCashFlow": 11483000,
      "link": "https://www.sec.gov/Archives/edgar/data/1045810/000104581013000075/0001045810-13-000075-index.htm",
      "finalLink": "https://www.sec.gov/Archives/edgar/data/1045810/000104581013000075/nvda2014q210q.htm"
    },
    {
      "date": "2013-04-28",
      "symbol": "NVDA",
      "reportedCurrency": "USD",
      "cik": "0001045810",
      "fillingDate": "2013-05-22",
      "acceptedDate": "2013-05-22 17:06:15",
      "calendarYear": "2014",
      "period": "Q1",
      "netIncome": 77891000,
      "depreciationAndAmortization": 59744000,
      "deferredIncomeTax": -3063000,
      "stockBasedCompensation": 33397000,
      "changeInWorkingCapital": 12813000,
      "accountsReceivables": 108476000,
      "inventory": 41510000,
      "accountsPayables": -53101000,
      "otherWorkingCapital": -84072000,
      "otherNonCashItems": -5132000,
      "netCashProvidedByOperatingActivities": 175650000,
      "investmentsInPropertyPlantAndEquipment": -65667000,
      "acquisitionsNet": 0,
      "purchasesOfInvestments": -541950000,
      "salesMaturitiesOfInvestments": 378281000,
      "otherInvestingActivites": -1450000,
      "netCashUsedForInvestingActivites": -230786000,
      "debtRepayment": -576000,
      "commonStockIssued": 22996000,
      "commonStockRepurchased": -100000000,
      "dividendsPaid": -46267000,
      "otherFinancingActivites": 30616000,
      "netCashUsedProvidedByFinancingActivities": -116227000,
      "effectOfForexChangesOnCash": 0,
      "netChangeInCash": -171363000,
      "cashAtEndOfPeriod": 561423000,
      "cashAtBeginningOfPeriod": 732786000,
      "operatingCashFlow": 175650000,
      "capitalExpenditure": -65667000,
      "freeCashFlow": 109983000,
      "link": "https://www.sec.gov/Archives/edgar/data/1045810/000104581013000054/0001045810-13-000054-index.htm",
      "finalLink": "https://www.sec.gov/Archives/edgar/data/1045810/000104581013000054/nvda2014q110q.htm"
    }
  ]
}