{
  "ticker": "AAPL",
  "endpoint": "analyst-estimates-annual",
  "fetched_at": "2025-09-05T14:21:05.603713",
  "data": [
    {
      "symbol": "AAPL",
      "date": "2029-09-28",
      "estimatedRevenueLow": 486965750000,
      "estimatedRevenueHigh": 494713249999,
      "estimatedRevenueAvg": 490839500000,
      "estimatedEbitdaLow": 159921010935,
      "estimatedEbitdaHigh": 162465313141,
      "estimatedEbitdaAvg": 161193162038,
      "estimatedEbitLow": 144474279743,
      "estimatedEbitHigh": 146772828424,
      "estimatedEbitAvg": 145623554084,
      "estimatedNetIncomeLow": 150491017955,
      "estimatedNetIncomeHigh": 166263822565,
      "estimatedNetIncomeAvg": 156623285685,
      "estimatedSgaExpenseLow": 31948768358,
      "estimatedSgaExpenseHigh": 32457065056,
      "estimatedSgaExpenseAvg": 32202916707,
      "estimatedEpsAvg": 10.165,
      "estimatedEpsHigh": 10.79068,
      "estimatedEpsLow": 9.76701,
      "numberAnalystEstimatedRevenue": 10,
      "numberAnalystsEstimatedEps": 10
    },
    {
      "symbol": "AAPL",
      "date": "2028-09-28",
      "estimatedRevenueLow": 445898207710,
      "estimatedRevenueHigh": 481512712841,
      "estimatedRevenueAvg": 459744587964,
      "estimatedEbitdaLow": 146434307035,
      "estimatedEbitdaHigh": 158130217198,
      "estimatedEbitdaAvg": 150981499785,
      "estimatedEbitLow": 132290253263,
      "estimatedEbitHigh": 142856458334,
      "estimatedEbitAvg": 136398233781,
      "estimatedNetIncomeLow": 130831675462,
      "estimatedNetIncomeHigh": 144544109609,
      "estimatedNetIncomeAvg": 136162876333,
      "estimatedSgaExpenseLow": 29254415838,
      "estimatedSgaExpenseHigh": 31591006398,
      "estimatedSgaExpenseAvg": 30162846862,
      "estimatedEpsAvg": 8.8371,
      "estimatedEpsHigh": 9.38105,
      "estimatedEpsLow": 8.4911,
      "numberAnalystEstimatedRevenue": 9,
      "numberAnalystsEstimatedEps": 9
    },
    {
      "symbol": "AAPL",
      "date": "2027-09-28",
      "estimatedRevenueLow": 457366830151,
      "estimatedRevenueHigh": 459828437970,
      "estimatedRevenueAvg": 458597634061,
      "estimatedEbitdaLow": 150200636997,
      "estimatedEbitdaHigh": 151009036378,
      "estimatedEbitdaAvg": 150604836688,
      "estimatedEbitLow": 135692794338,
      "estimatedEbitHigh": 136423110622,
      "estimatedEbitAvg": 136057952480,
      "estimatedNetIncomeLow": 121397452974,
      "estimatedNetIncomeHigh": 146044087657,
      "estimatedNetIncomeAvg": 124497449910,
      "estimatedSgaExpenseLow": 30006847321,
      "estimatedSgaExpenseHigh": 30168348080,
      "estimatedSgaExpenseAvg": 30087597701,
      "estimatedEpsAvg": 8.60984,
      "estimatedEpsHigh": 9.4784,
      "estimatedEpsLow": 7.87881,
      "numberAnalystEstimatedRevenue": 20,
      "numberAnalystsEstimatedEps": 19
    },
    {
      "symbol": "AAPL",
      "date": "2026-09-28",
      "estimatedRevenueLow": 429758127392,
      "estimatedRevenueHigh": 450239783256,
      "estimatedRevenueAvg": 436677054921,
      "estimatedEbitdaLow": 141133856313,
      "estimatedEbitdaHigh": 147860093449,
      "estimatedEbitdaAvg": 143406052838,
      "estimatedEbitLow": 127501771775,
      "estimatedEbitHigh": 133578323317,
      "estimatedEbitAvg": 129554497396,
      "estimatedNetIncomeLow": 118317528865,
      "estimatedNetIncomeHigh": 125839760844,
      "estimatedNetIncomeAvg": 122078644854.5,
      "estimatedSgaExpenseLow": 28195500118,
      "estimatedSgaExpenseHigh": 29539257208,
      "estimatedSgaExpenseAvg": 28649435971,
      "estimatedEpsAvg": 7.94336,
      "estimatedEpsHigh": 8.16712,
      "estimatedEpsLow": 7.67892,
      "numberAnalystEstimatedRevenue": 28,
      "numberAnalystsEstimatedEps": 29
    },
    {
      "symbol": "AAPL",
      "date": "2025-09-28",
      "estimatedRevenueLow": 406240486505,
      "estimatedRevenueHigh": 418892689715,
      "estimatedRevenueAvg": 414893545866,
      "estimatedEbitdaLow": 133410592602,
      "estimatedEbitdaHigh": 137565614034,
      "estimatedEbitdaAvg": 136252283215,
      "estimatedEbitLow": 120524496210,
      "estimatedEbitHigh": 124278185142,
      "estimatedEbitAvg": 123091708624,
      "estimatedNetIncomeLow": 111546749678,
      "estimatedNetIncomeHigh": 114636689050,
      "estimatedNetIncomeAvg": 113091719364,
      "estimatedSgaExpenseLow": 26652558626,
      "estimatedSgaExpenseHigh": 27482642281,
      "estimatedSgaExpenseAvg": 27220267113,
      "estimatedEpsAvg": 7.36984,
      "estimatedEpsHigh": 7.44003,
      "estimatedEpsLow": 7.23949,
      "numberAnalystEstimatedRevenue": 25,
      "numberAnalystsEstimatedEps": 27
    },
    {
      "symbol": "AAPL",
      "date": "2024-09-28",
      "estimatedRevenueLow": 389950945023,
      "estimatedRevenueHigh": 392209907768,
      "estimatedRevenueAvg": 390480701773,
      "estimatedEbitdaLow": 128061058386,
      "estimatedEbitdaHigh": 128802908518,
      "estimatedEbitdaAvg": 128235032090,
      "estimatedEbitLow": 115691672191,
      "estimatedEbitHigh": 116361867201,
      "estimatedEbitAvg": 115848841817,
      "estimatedNetIncomeLow": 94590757453,
      "estimatedNetIncomeHigh": 105866401375,
      "estimatedNetIncomeAvg": 97294000000,
      "estimatedSgaExpenseLow": 25583837084,
      "estimatedSgaExpenseHigh": 25732042738,
      "estimatedSgaExpenseAvg": 25618593277,
      "estimatedEpsAvg": 6.70821,
      "estimatedEpsHigh": 6.87083,
      "estimatedEpsLow": 6.13903,
      "numberAnalystEstimatedRevenue": 25,
      "numberAnalystsEstimatedEps": 26
    },
    {
      "symbol": "AAPL",
      "date": "2023-09-28",
      "estimatedRevenueLow": 365223745074,
      "estimatedRevenueHigh": 386415277467,
      "estimatedRevenueAvg": 383094279806,
      "estimatedEbitdaLow": 110816277291,
      "estimatedEbitdaHigh": 166224415938,
      "estimatedEbitdaAvg": 138520346615,
      "estimatedEbitLow": 99597027281,
      "estimatedEbitHigh": 149395540924,
      "estimatedEbitAvg": 124496284103,
      "estimatedNetIncomeLow": 80311199998,
      "estimatedNetIncomeHigh": 120466800001,
      "estimatedNetIncomeAvg": 100389000000,
      "estimatedSgaExpenseLow": 20384820993,
      "estimatedSgaExpenseHigh": 30577231491,
      "estimatedSgaExpenseAvg": 25481026242,
      "estimatedEpsAvg": 6.0576,
      "estimatedEpsHigh": 6.43046,
      "estimatedEpsLow": 5.82043,
      "numberAnalystEstimatedRevenue": 35,
      "numberAnalystsEstimatedEps": 36
    },
    {
      "symbol": "AAPL",
      "date": "2022-09-28",
      "estimatedRevenueLow": 383528516259,
      "estimatedRevenueHigh": 407883908152,
      "estimatedRevenueAvg": 392776831583,
      "estimatedEbitdaLow": 100742070266,
      "estimatedEbitdaHigh": 151113105399,
      "estimatedEbitdaAvg": 125927587833,
      "estimatedEbitLow": 90542752075,
      "estimatedEbitHigh": 135814128114,
      "estimatedEbitAvg": 113178440095,
      "estimatedNetIncomeLow": 76226527763,
      "estimatedNetIncomeHigh": 114339791647,
      "estimatedNetIncomeAvg": 95283159705,
      "estimatedSgaExpenseLow": 18531655449,
      "estimatedSgaExpenseHigh": 27797483175,
      "estimatedSgaExpenseAvg": 23164569312,
      "estimatedEpsAvg": 6.09835,
      "estimatedEpsHigh": 6.40327,
      "estimatedEpsLow": 5.91168,
      "numberAnalystEstimatedRevenue": 10,
      "numberAnalystsEstimatedEps": 16
    },
    {
      "symbol": "AAPL",
      "date": "2021-09-28",
      "estimatedRevenueLow": 357792137980,
      "estimatedRevenueHigh": 380513180529,
      "estimatedRevenueAvg": 366419852406,
      "estimatedEbitdaLow": 85099128888,
      "estimatedEbitdaHigh": 127648693332,
      "estimatedEbitdaAvg": 106373911110,
      "estimatedEbitLow": 76221262221,
      "estimatedEbitHigh": 114331893331,
      "estimatedEbitAvg": 95276577776,
      "estimatedNetIncomeLow": 65425795554,
      "estimatedNetIncomeHigh": 98138693331,
      "estimatedNetIncomeAvg": 81782244443,
      "estimatedSgaExpenseLow": 14849137776,
      "estimatedSgaExpenseHigh": 22273706665,
      "estimatedSgaExpenseAvg": 18561422221,
      "estimatedEpsAvg": 5.60786,
      "estimatedEpsHigh": 5.88826,
      "estimatedEpsLow": 5.4362,
      "numberAnalystEstimatedRevenue": 12,
      "numberAnalystsEstimatedEps": 11
    },
    {
      "symbol": "AAPL",
      "date": "2020-09-28",
      "estimatedRevenueLow": 266870190478,
      "estimatedRevenueHigh": 283817373798,
      "estimatedRevenueAvg": 273305434710,
      "estimatedEbitdaLow": 58883296895,
      "estimatedEbitdaHigh": 88324945342,
      "estimatedEbitdaAvg": 73604121119,
      "estimatedEbitLow": 49414904605,
      "estimatedEbitHigh": 74122356909,
      "estimatedEbitAvg": 61768630757,
      "estimatedNetIncomeLow": 42547628806,
      "estimatedNetIncomeHigh": 63821443210,
      "estimatedNetIncomeAvg": 53184536008,
      "estimatedSgaExpenseLow": 13621276088,
      "estimatedSgaExpenseHigh": 20431914134,
      "estimatedSgaExpenseAvg": 17026595111,
      "estimatedEpsAvg": 3.24619,
      "estimatedEpsHigh": 3.4085,
      "estimatedEpsLow": 3.14682,
      "numberAnalystEstimatedRevenue": 11,
      "numberAnalystsEstimatedEps": 11
    },
    {
      "symbol": "AAPL",
      "date": "2019-09-28",
      "estimatedRevenueLow": 252958943766,
      "estimatedRevenueHigh": 269022714638,
      "estimatedRevenueAvg": 259058735507,
      "estimatedEbitdaLow": 61938363473,
      "estimatedEbitdaHigh": 92907545213,
      "estimatedEbitdaAvg": 77422954344,
      "estimatedEbitLow": 49174177910,
      "estimatedEbitHigh": 73761266868,
      "estimatedEbitAvg": 61467722389,
      "estimatedNetIncomeLow": 42760601526,
      "estimatedNetIncomeHigh": 64140902290,
      "estimatedNetIncomeAvg": 53450751908,
      "estimatedSgaExpenseLow": 13953155108,
      "estimatedSgaExpenseHigh": 20929732663,
      "estimatedSgaExpenseAvg": 17441443886,
      "estimatedEpsAvg": 2.91939,
      "estimatedEpsHigh": 3.06536,
      "estimatedEpsLow": 2.83003,
      "numberAnalystEstimatedRevenue": 10,
      "numberAnalystsEstimatedEps": 16
    },
    {
      "symbol": "AAPL",
      "date": "2018-09-28",
      "estimatedRevenueLow": 258293332828,
      "estimatedRevenueHigh": 274695855920,
      "estimatedRevenueAvg": 264521756757,
      "estimatedEbitdaLow": 65538089813,
      "estimatedEbitdaHigh": 98307134722,
      "estimatedEbitdaAvg": 81922612268,
      "estimatedEbitLow": 52617542308,
      "estimatedEbitHigh": 78926313461,
      "estimatedEbitAvg": 65771927885,
      "estimatedNetIncomeLow": 45982107012,
      "estimatedNetIncomeHigh": 68973160521,
      "estimatedNetIncomeAvg": 57477633767,
      "estimatedSgaExpenseLow": 13308448708,
      "estimatedSgaExpenseHigh": 19962673062,
      "estimatedSgaExpenseAvg": 16635560885,
      "estimatedEpsAvg": 2.93697,
      "estimatedEpsHigh": 3.08382,
      "estimatedEpsLow": 2.84707,
      "numberAnalystEstimatedRevenue": 6,
      "numberAnalystsEstimatedEps": 5
    },
    {
      "symbol": "AAPL",
      "date": "2017-09-28",
      "estimatedRevenueLow": 222106125174,
      "estimatedRevenueHigh": 236210634985,
      "estimatedRevenueAvg": 227461939394,
      "estimatedEbitdaLow": 60576087762,
      "estimatedEbitdaHigh": 90864131644,
      "estimatedEbitdaAvg": 75720109703,
      "estimatedEbitLow": 49125945973,
      "estimatedEbitHigh": 73688918960,
      "estimatedEbitAvg": 61407432467,
      "estimatedNetIncomeLow": 38584925632,
      "estimatedNetIncomeHigh": 57877388448,
      "estimatedNetIncomeAvg": 48231157040,
      "estimatedSgaExpenseLow": 11773599361,
      "estimatedSgaExpenseHigh": 17660399042,
      "estimatedSgaExpenseAvg": 14716999202,
      "estimatedEpsAvg": 2.24805,
      "estimatedEpsHigh": 2.36045,
      "estimatedEpsLow": 2.17924,
      "numberAnalystEstimatedRevenue": 11,
      "numberAnalystsEstimatedEps": 10
    },
    {
      "symbol": "AAPL",
      "date": "2016-09-28",
      "estimatedRevenueLow": 210641470990,
      "estimatedRevenueHigh": 224017935470,
      "estimatedRevenueAvg": 215720829268,
      "estimatedEbitdaLow": 57835982111,
      "estimatedEbitdaHigh": 86753973169,
      "estimatedEbitdaAvg": 72294977640,
      "estimatedEbitLow": 46764847994,
      "estimatedEbitHigh": 70147271993,
      "estimatedEbitAvg": 58456059994,
      "estimatedNetIncomeLow": 35701199794,
      "estimatedNetIncomeHigh": 53551799691,
      "estimatedNetIncomeAvg": 44626499743,
      "estimatedSgaExpenseLow": 11326433953,
      "estimatedSgaExpenseHigh": 16989650929,
      "estimatedSgaExpenseAvg": 14158042441,
      "estimatedEpsAvg": 2.06782,
      "estimatedEpsHigh": 2.17121,
      "estimatedEpsLow": 2.00452,
      "numberAnalystEstimatedRevenue": 7,
      "numberAnalystsEstimatedEps": 8
    },
    {
      "symbol": "AAPL",
      "date": "2015-09-28",
      "estimatedRevenueLow": 227742671694,
      "estimatedRevenueHigh": 242205121772,
      "estimatedRevenueAvg": 233234404255,
      "estimatedEbitdaLow": 65528314429,
      "estimatedEbitdaHigh": 98292471646,
      "estimatedEbitdaAvg": 81910393038,
      "estimatedEbitLow": 54727046220,
      "estimatedEbitHigh": 82090569332,
      "estimatedEbitAvg": 68408807776,
      "estimatedNetIncomeLow": 41335620747,
      "estimatedNetIncomeHigh": 62003431120,
      "estimatedNetIncomeAvg": 51669525934,
      "estimatedSgaExpenseLow": 11206957292,
      "estimatedSgaExpenseHigh": 16810435937,
      "estimatedSgaExpenseAvg": 14008696615,
      "estimatedEpsAvg": 2.28249,
      "estimatedEpsHigh": 2.39662,
      "estimatedEpsLow": 2.21262,
      "numberAnalystEstimatedRevenue": 6,
      "numberAnalystsEstimatedEps": 5
    },
    {
      "symbol": "AAPL",
      "date": "2014-09-28",
      "estimatedRevenueLow": 142688813098,
      "estimatedRevenueHigh": 214033219648,
      "estimatedRevenueAvg": 178361016373,
      "estimatedEbitdaLow": 48311071150,
      "estimatedEbitdaHigh": 72466606725,
      "estimatedEbitdaAvg": 60388838938,
      "estimatedEbitLow": 41423025373,
      "estimatedEbitHigh": 62134538061,
      "estimatedEbitAvg": 51778781717,
      "estimatedNetIncomeLow": 31077438948,
      "estimatedNetIncomeHigh": 46616158423,
      "estimatedNetIncomeAvg": 38846798686,
      "estimatedSgaExpenseLow": 8896323083,
      "estimatedSgaExpenseHigh": 13344484625,
      "estimatedSgaExpenseAvg": 11120403854,
      "estimatedEpsAvg": 1.445,
      "estimatedEpsHigh": 1.73,
      "estimatedEpsLow": 1.16,
      "numberAnalystEstimatedRevenue": 13,
      "numberAnalystsEstimatedEps": 13
    },
    {
      "symbol": "AAPL",
      "date": "2013-09-28",
      "estimatedRevenueLow": 136071463842,
      "estimatedRevenueHigh": 204107195765,
      "estimatedRevenueAvg": 170089329804,
      "estimatedEbitdaLow": 45114743880,
      "estimatedEbitdaHigh": 67672115819,
      "estimatedEbitdaAvg": 56393429850,
      "estimatedEbitLow": 38492569013,
      "estimatedEbitHigh": 57738853520,
      "estimatedEbitAvg": 48115711267,
      "estimatedNetIncomeLow": 28943217028,
      "estimatedNetIncomeHigh": 43414825544,
      "estimatedNetIncomeAvg": 36179021286,
      "estimatedSgaExpenseLow": 8631207944,
      "estimatedSgaExpenseHigh": 12946811914,
      "estimatedSgaExpenseAvg": 10789009930,
      "estimatedEpsAvg": 1.375,
      "estimatedEpsHigh": 1.65,
      "estimatedEpsLow": 1.1,
      "numberAnalystEstimatedRevenue": 10,
      "numberAnalystsEstimatedEps": 10
    },
    {
      "symbol": "AAPL",
      "date": "2012-09-28",
      "estimatedRevenueLow": 128156865993,
      "estimatedRevenueHigh": 192235298991,
      "estimatedRevenueAvg": 160196082492,
      "estimatedEbitdaLow": 48165863290,
      "estimatedEbitdaHigh": 72248794936,
      "estimatedEbitdaAvg": 60207329113,
      "estimatedEbitLow": 44152594141,
      "estimatedEbitHigh": 66228891212,
      "estimatedEbitAvg": 55190742677,
      "estimatedNetIncomeLow": 33450485467,
      "estimatedNetIncomeHigh": 50175728202,
      "estimatedNetIncomeAvg": 41813106835,
      "estimatedSgaExpenseLow": 8294406322,
      "estimatedSgaExpenseHigh": 12441609482,
      "estimatedSgaExpenseAvg": 10368007903,
      "estimatedEpsAvg": 1.59,
      "estimatedEpsHigh": 1.91,
      "estimatedEpsLow": 1.27,
      "numberAnalystEstimatedRevenue": 16,
      "numberAnalystsEstimatedEps": 16
    },
    {
      "symbol": "AAPL",
      "date": "2011-09-28",
      "estimatedRevenueLow": 84668972076,
      "estimatedRevenueHigh": 127003458115,
      "estimatedRevenueAvg": 105836215096,
      "estimatedEbitdaLow": 27829630700,
      "estimatedEbitdaHigh": 41744446050,
      "estimatedEbitdaAvg": 34787038375,
      "estimatedEbitLow": 26224114980,
      "estimatedEbitHigh": 39336172470,
      "estimatedEbitAvg": 32780143725,
      "estimatedNetIncomeLow": 19972314851,
      "estimatedNetIncomeHigh": 29958472278,
      "estimatedNetIncomeAvg": 24965393565,
      "estimatedSgaExpenseLow": 5187821520,
      "estimatedSgaExpenseHigh": 7781732282,
      "estimatedSgaExpenseAvg": 6484776901,
      "estimatedEpsAvg": 0.8,
      "estimatedEpsHigh": 0.96,
      "estimatedEpsLow": 0.64,
      "numberAnalystEstimatedRevenue": 10,
      "numberAnalystsEstimatedEps": 10
    },
    {
      "symbol": "AAPL",
      "date": "2010-09-28",
      "estimatedRevenueLow": 51133805598,
      "estimatedRevenueHigh": 76700708397,
      "estimatedRevenueAvg": 63917256998,
      "estimatedEbitdaLow": 14640464486,
      "estimatedEbitdaHigh": 21960696730,
      "estimatedEbitdaAvg": 18300580608,
      "estimatedEbitLow": 13724537177,
      "estimatedEbitHigh": 20586805767,
      "estimatedEbitAvg": 17155671472,
      "estimatedNetIncomeLow": 10631856299,
      "estimatedNetIncomeHigh": 15947784450,
      "estimatedNetIncomeAvg": 13289820375,
      "estimatedSgaExpenseLow": 3911780741,
      "estimatedSgaExpenseHigh": 5867671113,
      "estimatedSgaExpenseAvg": 4889725927,
      "estimatedEpsAvg": 0.43,
      "estimatedEpsHigh": 0.52,
      "estimatedEpsLow": 0.34,
      "numberAnalystEstimatedRevenue": 12,
      "numberAnalystsEstimatedEps": 12
    },
    {
      "symbol": "AAPL",
      "date": "2009-09-28",
      "estimatedRevenueLow": 33020178101,
      "estimatedRevenueHigh": 49530267154,
      "estimatedRevenueAvg": 41275222628,
      "estimatedEbitdaLow": 7880186154,
      "estimatedEbitdaHigh": 11820279232,
      "estimatedEbitdaAvg": 9850232693,
      "estimatedEbitLow": 7233683475,
      "estimatedEbitHigh": 10850525212,
      "estimatedEbitAvg": 9042104344,
      "estimatedNetIncomeLow": 5258282440,
      "estimatedNetIncomeHigh": 7887423661,
      "estimatedNetIncomeAvg": 6572853051,
      "estimatedSgaExpenseLow": 2968463095,
      "estimatedSgaExpenseHigh": 4452694642,
      "estimatedSgaExpenseAvg": 3710578869,
      "estimatedEpsAvg": 0.185,
      "estimatedEpsHigh": 0.22,
      "estimatedEpsLow": 0.15,
      "numberAnalystEstimatedRevenue": 19,
      "numberAnalystsEstimatedEps": 19
    },
    {
      "symbol": "AAPL",
      "date": "2008-09-28",
      "estimatedRevenueLow": 26765317646,
      "estimatedRevenueHigh": 40147976469,
      "estimatedRevenueAvg": 33456647058,
      "estimatedEbitdaLow": 4898933332,
      "estimatedEbitdaHigh": 7348399998,
      "estimatedEbitdaAvg": 6123666665,
      "estimatedEbitLow": 4161853332,
      "estimatedEbitHigh": 6242779998,
      "estimatedEbitAvg": 5202316665,
      "estimatedNetIncomeLow": 3225986666,
      "estimatedNetIncomeHigh": 4838979998,
      "estimatedNetIncomeAvg": 4032483332,
      "estimatedSgaExpenseLow": 2603286666,
      "estimatedSgaExpenseHigh": 3904929998,
      "estimatedSgaExpenseAvg": 3254108332,
      "estimatedEpsAvg": 0.145,
      "estimatedEpsHigh": 0.17,
      "estimatedEpsLow": 0.12,
      "numberAnalystEstimatedRevenue": 15,
      "numberAnalystsEstimatedEps": 15
    },
    {
      "symbol": "AAPL",
      "date": "2007-09-28",
      "estimatedRevenueLow": 18693939340,
      "estimatedRevenueHigh": 28040909010,
      "estimatedRevenueAvg": 23367424175,
      "estimatedEbitdaLow": 4015137390,
      "estimatedEbitdaHigh": 6022706085,
      "estimatedEbitdaAvg": 5018921738,
      "estimatedEbitLow": 3368397679,
      "estimatedEbitHigh": 5052596520,
      "estimatedEbitAvg": 4210497100,
      "estimatedNetIncomeLow": 2626230723,
      "estimatedNetIncomeHigh": 3939346085,
      "estimatedNetIncomeAvg": 3282788404,
      "estimatedSgaExpenseLow": 2030310723,
      "estimatedSgaExpenseHigh": 3045466083,
      "estimatedSgaExpenseAvg": 2537888404,
      "estimatedEpsAvg": 0.105,
      "estimatedEpsHigh": 0.13,
      "estimatedEpsLow": 0.08,
      "numberAnalystEstimatedRevenue": 10,
      "numberAnalystsEstimatedEps": 10
    },
    {
      "symbol": "AAPL",
      "date": "2005-09-28",
      "estimatedRevenueLow": 13626659998,
      "estimatedRevenueHigh": 20439989997,
      "estimatedRevenueAvg": 17033324998,
      "estimatedEbitdaLow": 1741024242,
      "estimatedEbitdaHigh": 2611536363,
      "estimatedEbitdaAvg": 2176280303,
      "estimatedEbitLow": 1443981817,
      "estimatedEbitHigh": 2165972726,
      "estimatedEbitAvg": 1804977272,
      "estimatedNetIncomeLow": 1170787878,
      "estimatedNetIncomeHigh": 1756181817,
      "estimatedNetIncomeAvg": 1463484848,
      "estimatedSgaExpenseLow": 1446545454,
      "estimatedSgaExpenseHigh": 2169818181,
      "estimatedSgaExpenseAvg": 1808181818,
      "estimatedEpsAvg": 0.055,
      "estimatedEpsHigh": 0.07,
      "estimatedEpsLow": 0.04,
      "numberAnalystEstimatedRevenue": 7,
      "numberAnalystsEstimatedEps": 7
    },
    {
      "symbol": "AAPL",
      "date": "2004-09-28",
      "estimatedRevenueLow": 7979799998,
      "estimatedRevenueHigh": 11969699998,
      "estimatedRevenueAvg": 9974749998,
      "estimatedEbitdaLow": 642402424,
      "estimatedEbitdaHigh": 963603636,
      "estimatedEbitdaAvg": 803003030,
      "estimatedEbitLow": 465852121,
      "estimatedEbitHigh": 698778181,
      "estimatedEbitAvg": 582315151,
      "estimatedNetIncomeLow": 364819393,
      "estimatedNetIncomeHigh": 547229090,
      "estimatedNetIncomeAvg": 456024242,
      "estimatedSgaExpenseLow": 1188962424,
      "estimatedSgaExpenseHigh": 1783443636,
      "estimatedSgaExpenseAvg": 1486203030,
      "estimatedEpsAvg": 0.005,
      "estimatedEpsHigh": 0.00525,
      "estimatedEpsLow": 0.00484695,
      "numberAnalystEstimatedRevenue": 19,
      "numberAnalystsEstimatedEps": 19
    },
    {
      "symbol": "AAPL",
      "date": "1998-09-28",
      "estimatedRevenueLow": 5646060000,
      "estimatedRevenueHigh": 8469090000,
      "estimatedRevenueAvg": 7057575000,
      "estimatedEbitdaLow": 394800000,
      "estimatedEbitdaHigh": 592200000,
      "estimatedEbitdaAvg": 493500000,
      "estimatedEbitLow": 237560000,
      "estimatedEbitHigh": 356340000,
      "estimatedEbitAvg": 296950000,
      "estimatedNetIncomeLow": 284560000,
      "estimatedNetIncomeHigh": 426840000,
      "estimatedNetIncomeAvg": 355700000,
      "estimatedSgaExpenseLow": 679240000,
      "estimatedSgaExpenseHigh": 1018860000,
      "estimatedSgaExpenseAvg": 849050000,
      "estimatedEpsAvg": 0.005,
      "estimatedEpsHigh": 0.00525,
      "estimatedEpsLow": 0.00484695,
      "numberAnalystEstimatedRevenue": 8,
      "numberAnalystsEstimatedEps": 8
    },
    {
      "symbol": "AAPL",
      "date": "1996-09-28",
      "estimatedRevenueLow": 9379790093,
      "estimatedRevenueHigh": 14069685139,
      "estimatedRevenueAvg": 11724737616,
      "estimatedEbitdaLow": -794399999,
      "estimatedEbitdaHigh": -379839999,
      "estimatedEbitdaAvg": -587119999,
      "estimatedEbitLow": -1147151999,
      "estimatedEbitHigh": -715807999,
      "estimatedEbitAvg": -931479999,
      "estimatedNetIncomeLow": -673919999,
      "estimatedNetIncomeHigh": -413280000,
      "estimatedNetIncomeAvg": -543600000,
      "estimatedSgaExpenseLow": 1390464000,
      "estimatedSgaExpenseHigh": 2085695998,
      "estimatedSgaExpenseAvg": 1738080000,
      "estimatedEpsAvg": -0.03,
      "estimatedEpsHigh": -0.02,
      "estimatedEpsLow": -0.04,
      "numberAnalystEstimatedRevenue": 16,
      "numberAnalystsEstimatedEps": 16
    }
  ]
}