{
  "ticker": "CRM",
  "endpoint": "analyst-estimates-annual",
  "fetched_at": "2025-09-05T14:21:39.834099",
  "data": [
    {
      "symbol": "CRM",
      "date": "2030-01-31",
      "estimatedRevenueLow": 59531653271,
      "estimatedRevenueHigh": 61640621840,
      "estimatedRevenueAvg": 60199000000,
      "estimatedEbitdaLow": 12371989500,
      "estimatedEbitdaHigh": 12810279646,
      "estimatedEbitdaAvg": 12510678857,
      "estimatedEbitLow": 5664517633,
      "estimatedEbitHigh": 5865188855,
      "estimatedEbitAvg": 5728016580,
      "estimatedNetIncomeLow": 18037710558,
      "estimatedNetIncomeHigh": 18871220799,
      "estimatedNetIncomeAvg": 18301460018,
      "estimatedSgaExpenseLow": 29511219408,
      "estimatedSgaExpenseHigh": 30556683976,
      "estimatedSgaExpenseAvg": 29842038639,
      "estimatedEpsAvg": 18.79,
      "estimatedEpsHigh": 19.37497,
      "estimatedEpsLow": 18.51921,
      "numberAnalystEstimatedRevenue": 19,
      "numberAnalystsEstimatedEps": 7
    },
    {
      "symbol": "CRM",
      "date": "2029-01-31",
      "estimatedRevenueLow": 55327446842,
      "estimatedRevenueHigh": 57287477179,
      "estimatedRevenueAvg": 55947664636,
      "estimatedEbitdaLow": 11498262752,
      "estimatedEbitdaHigh": 11905600251,
      "estimatedEbitdaAvg": 11627157678,
      "estimatedEbitLow": 5264481683,
      "estimatedEbitHigh": 5450981231,
      "estimatedEbitAvg": 5323496248,
      "estimatedNetIncomeLow": 17246374517,
      "estimatedNetIncomeHigh": 18043311058,
      "estimatedNetIncomeAvg": 17498552857,
      "estimatedSgaExpenseLow": 27427096903,
      "estimatedSgaExpenseHigh": 28398729339,
      "estimatedSgaExpenseAvg": 27734553229,
      "estimatedEpsAvg": 17.96566,
      "estimatedEpsHigh": 18.52496,
      "estimatedEpsLow": 17.70675,
      "numberAnalystEstimatedRevenue": 15,
      "numberAnalystsEstimatedEps": 7
    },
    {
      "symbol": "CRM",
      "date": "2028-01-31",
      "estimatedRevenueLow": 49344544267,
      "estimatedRevenueHigh": 49400509742,
      "estimatedRevenueAvg": 49372527005,
      "estimatedEbitdaLow": 10254883747,
      "estimatedEbitdaHigh": 10266514606,
      "estimatedEbitdaAvg": 10260699176,
      "estimatedEbitLow": 4695200380,
      "estimatedEbitHigh": 4700525571,
      "estimatedEbitAvg": 4697862976,
      "estimatedNetIncomeLow": 12552181512,
      "estimatedNetIncomeHigh": 16092535156,
      "estimatedNetIncomeAvg": 14322358334,
      "estimatedSgaExpenseLow": 24461233519,
      "estimatedSgaExpenseHigh": 24488976901,
      "estimatedSgaExpenseAvg": 24475105211,
      "estimatedEpsAvg": 14.54118,
      "estimatedEpsHigh": 16.52211,
      "estimatedEpsLow": 12.88725,
      "numberAnalystEstimatedRevenue": 28,
      "numberAnalystsEstimatedEps": 17
    },
    {
      "symbol": "CRM",
      "date": "2027-01-31",
      "estimatedRevenueLow": 44222206306,
      "estimatedRevenueHigh": 46132733654,
      "estimatedRevenueAvg": 44972413380,
      "estimatedEbitdaLow": 9190349033,
      "estimatedEbitdaHigh": 9587398720,
      "estimatedEbitdaAvg": 9346258596,
      "estimatedEbitLow": 4207802969,
      "estimatedEbitHigh": 4389592240,
      "estimatedEbitAvg": 4279186190,
      "estimatedNetIncomeLow": 11995676872,
      "estimatedNetIncomeHigh": 13185408133,
      "estimatedNetIncomeAvg": 12590542502.5,
      "estimatedSgaExpenseLow": 21921971948,
      "estimatedSgaExpenseHigh": 22869064606,
      "estimatedSgaExpenseAvg": 22293866971,
      "estimatedEpsAvg": 12.70959,
      "estimatedEpsHigh": 13.53738,
      "estimatedEpsLow": 12.31589,
      "numberAnalystEstimatedRevenue": 40,
      "numberAnalystsEstimatedEps": 33
    },
    {
      "symbol": "CRM",
      "date": "2026-01-31",
      "estimatedRevenueLow": 41168743625,
      "estimatedRevenueHigh": 41298897726,
      "estimatedRevenueAvg": 41218802895,
      "estimatedEbitdaLow": 8555772196,
      "estimatedEbitdaHigh": 8582821087,
      "estimatedEbitdaAvg": 8566175616,
      "estimatedEbitLow": 3917261849,
      "estimatedEbitHigh": 3929646188,
      "estimatedEbitAvg": 3922025057,
      "estimatedNetIncomeLow": 10919523751,
      "estimatedNetIncomeHigh": 11085717371,
      "estimatedNetIncomeAvg": 11002620561,
      "estimatedSgaExpenseLow": 20408299772,
      "estimatedSgaExpenseHigh": 20472820174,
      "estimatedSgaExpenseAvg": 20433115311,
      "estimatedEpsAvg": 11.34149,
      "estimatedEpsHigh": 11.38164,
      "estimatedEpsLow": 11.21101,
      "numberAnalystEstimatedRevenue": 39,
      "numberAnalystsEstimatedEps": 32
    },
    {
      "symbol": "CRM",
      "date": "2025-01-31",
      "estimatedRevenueLow": 37886595755,
      "estimatedRevenueHigh": 38096687784,
      "estimatedRevenueAvg": 37956626432,
      "estimatedEbitdaLow": 7873669537,
      "estimatedEbitdaHigh": 7917331291,
      "estimatedEbitdaAvg": 7888223455,
      "estimatedEbitLow": 3604961023,
      "estimatedEbitHigh": 3624951565,
      "estimatedEbitAvg": 3611624537,
      "estimatedNetIncomeLow": 9717052569,
      "estimatedNetIncomeHigh": 10009145430,
      "estimatedNetIncomeAvg": 9863098999.5,
      "estimatedSgaExpenseLow": 18781263051,
      "estimatedSgaExpenseHigh": 18885410536,
      "estimatedSgaExpenseAvg": 18815978880,
      "estimatedEpsAvg": 10.02642,
      "estimatedEpsHigh": 10.27633,
      "estimatedEpsLow": 9.97644,
      "numberAnalystEstimatedRevenue": 33,
      "numberAnalystsEstimatedEps": 34
    },
    {
      "symbol": "CRM",
      "date": "2024-01-31",
      "estimatedRevenueLow": 34790063781,
      "estimatedRevenueHigh": 34820081092,
      "estimatedRevenueAvg": 34800069552,
      "estimatedEbitdaLow": 3582754353,
      "estimatedEbitdaHigh": 5374131535,
      "estimatedEbitdaAvg": 4478442944,
      "estimatedEbitLow": 146493679,
      "estimatedEbitHigh": 387178356,
      "estimatedEbitAvg": 266836018,
      "estimatedNetIncomeLow": 4443966741,
      "estimatedNetIncomeHigh": 6820033258,
      "estimatedNetIncomeAvg": 5632000000,
      "estimatedSgaExpenseLow": 11982642649,
      "estimatedSgaExpenseHigh": 17973963973,
      "estimatedSgaExpenseAvg": 14978303311,
      "estimatedEpsAvg": 8.19661,
      "estimatedEpsHigh": 8.37654,
      "estimatedEpsLow": 8.17662,
      "numberAnalystEstimatedRevenue": 29,
      "numberAnalystsEstimatedEps": 31
    },
    {
      "symbol": "CRM",
      "date": "2023-01-31",
      "estimatedRevenueLow": 34790063781,
      "estimatedRevenueHigh": 34820081092,
      "estimatedRevenueAvg": 34800069552,
      "estimatedEbitdaLow": 3582754353,
      "estimatedEbitdaHigh": 5374131535,
      "estimatedEbitdaAvg": 4478442944,
      "estimatedEbitLow": 146493679,
      "estimatedEbitHigh": 387178356,
      "estimatedEbitAvg": 266836018,
      "estimatedNetIncomeLow": 4443966741,
      "estimatedNetIncomeHigh": 6820033258,
      "estimatedNetIncomeAvg": 5632000000,
      "estimatedSgaExpenseLow": 11982642649,
      "estimatedSgaExpenseHigh": 17973963973,
      "estimatedSgaExpenseAvg": 14978303311,
      "estimatedEpsAvg": 8.19661,
      "estimatedEpsHigh": 8.37654,
      "estimatedEpsLow": 8.17662,
      "numberAnalystEstimatedRevenue": 29,
      "numberAnalystsEstimatedEps": 31
    },
    {
      "symbol": "CRM",
      "date": "2022-01-31",
      "estimatedRevenueLow": 26167276762,
      "estimatedRevenueHigh": 26773971712,
      "estimatedRevenueAvg": 26401603111,
      "estimatedEbitdaLow": 2950173565,
      "estimatedEbitdaHigh": 4425260350,
      "estimatedEbitdaAvg": 3687716958,
      "estimatedEbitLow": 516093014,
      "estimatedEbitHigh": 774139524,
      "estimatedEbitAvg": 645116270,
      "estimatedNetIncomeLow": 959696332,
      "estimatedNetIncomeHigh": 1439544499,
      "estimatedNetIncomeAvg": 1199620416,
      "estimatedSgaExpenseLow": 7283987778,
      "estimatedSgaExpenseHigh": 10925981667,
      "estimatedSgaExpenseAvg": 9104984723,
      "estimatedEpsAvg": 4.68908,
      "estimatedEpsHigh": 4.77506,
      "estimatedEpsLow": 4.63498,
      "numberAnalystEstimatedRevenue": 24,
      "numberAnalystsEstimatedEps": 15
    },
    {
      "symbol": "CRM",
      "date": "2021-01-31",
      "estimatedRevenueLow": 20916695435,
      "estimatedRevenueHigh": 21401654325,
      "estimatedRevenueAvg": 21104003152,
      "estimatedEbitdaLow": 3050354127,
      "estimatedEbitdaHigh": 4575531191,
      "estimatedEbitdaAvg": 3812942659,
      "estimatedEbitLow": 44558944,
      "estimatedEbitHigh": 234380861,
      "estimatedEbitAvg": 139469903,
      "estimatedNetIncomeLow": 2144676511,
      "estimatedNetIncomeHigh": 3420729053,
      "estimatedNetIncomeAvg": 2782702782,
      "estimatedSgaExpenseLow": 7615855100,
      "estimatedSgaExpenseHigh": 11423782652,
      "estimatedSgaExpenseAvg": 9519818876,
      "estimatedEpsAvg": 4.64352,
      "estimatedEpsHigh": 4.72866,
      "estimatedEpsLow": 4.58994,
      "numberAnalystEstimatedRevenue": 14,
      "numberAnalystsEstimatedEps": 20
    },
    {
      "symbol": "CRM",
      "date": "2020-01-31",
      "estimatedRevenueLow": 16851423446,
      "estimatedRevenueHigh": 17242127974,
      "estimatedRevenueAvg": 17002326904,
      "estimatedEbitdaLow": 1513897039,
      "estimatedEbitdaHigh": 2270845558,
      "estimatedEbitdaAvg": 1892371299,
      "estimatedEbitLow": 242880725,
      "estimatedEbitHigh": 364321090,
      "estimatedEbitAvg": 303600908,
      "estimatedNetIncomeLow": 309359155,
      "estimatedNetIncomeHigh": 558175098,
      "estimatedNetIncomeAvg": 433767127,
      "estimatedSgaExpenseLow": 4933951126,
      "estimatedSgaExpenseHigh": 7400926691,
      "estimatedSgaExpenseAvg": 6167438909,
      "estimatedEpsAvg": 2.89647,
      "estimatedEpsHigh": 2.94958,
      "estimatedEpsLow": 2.86305,
      "numberAnalystEstimatedRevenue": 14,
      "numberAnalystsEstimatedEps": 14
    },
    {
      "symbol": "CRM",
      "date": "2019-01-31",
      "estimatedRevenueLow": 13119424059,
      "estimatedRevenueHigh": 13423601234,
      "estimatedRevenueAvg": 13236907692,
      "estimatedEbitdaLow": 926952262,
      "estimatedEbitdaHigh": 1390428394,
      "estimatedEbitdaAvg": 1158690328,
      "estimatedEbitLow": 233164826,
      "estimatedEbitHigh": 349747240,
      "estimatedEbitAvg": 291456033,
      "estimatedNetIncomeLow": 365190973,
      "estimatedNetIncomeHigh": 547786459,
      "estimatedNetIncomeAvg": 456488716,
      "estimatedSgaExpenseLow": 3834420390,
      "estimatedSgaExpenseHigh": 5751630586,
      "estimatedSgaExpenseAvg": 4793025488,
      "estimatedEpsAvg": 2.60661,
      "estimatedEpsHigh": 2.6544,
      "estimatedEpsLow": 2.57653,
      "numberAnalystEstimatedRevenue": 13,
      "numberAnalystsEstimatedEps": 16
    },
    {
      "symbol": "CRM",
      "date": "2018-01-31",
      "estimatedRevenueLow": 10349429001,
      "estimatedRevenueHigh": 10589383138,
      "estimatedRevenueAvg": 10442107500,
      "estimatedEbitdaLow": 692111725,
      "estimatedEbitdaHigh": 1038167588,
      "estimatedEbitdaAvg": 865139657,
      "estimatedEbitLow": 92648435,
      "estimatedEbitHigh": 167715022,
      "estimatedEbitAvg": 130181729,
      "estimatedNetIncomeLow": -11881006,
      "estimatedNetIncomeHigh": 35944461,
      "estimatedNetIncomeAvg": 12031728,
      "estimatedSgaExpenseLow": 4187927836,
      "estimatedSgaExpenseHigh": 6281891756,
      "estimatedSgaExpenseAvg": 5234909796,
      "estimatedEpsAvg": 1.3367,
      "estimatedEpsHigh": 1.36121,
      "estimatedEpsLow": 1.32128,
      "numberAnalystEstimatedRevenue": 8,
      "numberAnalystsEstimatedEps": 7
    },
    {
      "symbol": "CRM",
      "date": "2017-01-31",
      "estimatedRevenueLow": 8298481562,
      "estimatedRevenueHigh": 8490883962,
      "estimatedRevenueAvg": 8372793953,
      "estimatedEbitdaLow": 528549661,
      "estimatedEbitdaHigh": 792824491,
      "estimatedEbitdaAvg": 660687076,
      "estimatedEbitLow": 81983873,
      "estimatedEbitHigh": 122975809,
      "estimatedEbitAvg": 102479841,
      "estimatedNetIncomeLow": 127671107,
      "estimatedNetIncomeHigh": 248994804,
      "estimatedNetIncomeAvg": 188332956,
      "estimatedSgaExpenseLow": 3439087247,
      "estimatedSgaExpenseHigh": 5158630872,
      "estimatedSgaExpenseAvg": 4298859060,
      "estimatedEpsAvg": 0.97909,
      "estimatedEpsHigh": 0.99704,
      "estimatedEpsLow": 0.96779,
      "numberAnalystEstimatedRevenue": 8,
      "numberAnalystsEstimatedEps": 7
    },
    {
      "symbol": "CRM",
      "date": "2016-01-31",
      "estimatedRevenueLow": 6589917473,
      "estimatedRevenueHigh": 6742706382,
      "estimatedRevenueAvg": 6648929778,
      "estimatedEbitdaLow": 435229615,
      "estimatedEbitdaHigh": 652844425,
      "estimatedEbitdaAvg": 544037020,
      "estimatedEbitLow": 25617675,
      "estimatedEbitHigh": 73242514,
      "estimatedEbitAvg": 49430095,
      "estimatedNetIncomeLow": -104088330,
      "estimatedNetIncomeHigh": -67053934,
      "estimatedNetIncomeAvg": -85571132,
      "estimatedSgaExpenseLow": 2791560877,
      "estimatedSgaExpenseHigh": 4187341317,
      "estimatedSgaExpenseAvg": 3489451097,
      "estimatedEpsAvg": 0.75327,
      "estimatedEpsHigh": 0.76708,
      "estimatedEpsLow": 0.74458,
      "numberAnalystEstimatedRevenue": 7,
      "numberAnalystsEstimatedEps": 8
    },
    {
      "symbol": "CRM",
      "date": "2015-01-31",
      "estimatedRevenueLow": 5320789829,
      "estimatedRevenueHigh": 5444153691,
      "estimatedRevenueAvg": 5368437174,
      "estimatedEbitdaLow": 176099178,
      "estimatedEbitdaHigh": 264148767,
      "estimatedEbitdaAvg": 220123973,
      "estimatedEbitLow": -224707432,
      "estimatedEbitHigh": -149804954,
      "estimatedEbitAvg": -187256193,
      "estimatedNetIncomeLow": -331599493,
      "estimatedNetIncomeHigh": -221066328,
      "estimatedNetIncomeAvg": -276332911,
      "estimatedSgaExpenseLow": 2376372301,
      "estimatedSgaExpenseHigh": 3564558451,
      "estimatedSgaExpenseAvg": 2970465376,
      "estimatedEpsAvg": 0.51869,
      "estimatedEpsHigh": 0.5282,
      "estimatedEpsLow": 0.51271,
      "numberAnalystEstimatedRevenue": 8,
      "numberAnalystsEstimatedEps": 7
    },
    {
      "symbol": "CRM",
      "date": "2014-01-31",
      "estimatedRevenueLow": 2684070426,
      "estimatedRevenueHigh": 4026105640,
      "estimatedRevenueAvg": 3355088033,
      "estimatedEbitdaLow": 72338091,
      "estimatedEbitdaHigh": 108507137,
      "estimatedEbitdaAvg": 90422614,
      "estimatedEbitLow": -222606222,
      "estimatedEbitHigh": -148404148,
      "estimatedEbitAvg": -185505185,
      "estimatedNetIncomeLow": -204321818,
      "estimatedNetIncomeHigh": -99736925,
      "estimatedNetIncomeAvg": -152029372,
      "estimatedSgaExpenseLow": 1734248240,
      "estimatedSgaExpenseHigh": 2601372360,
      "estimatedSgaExpenseAvg": 2167810300,
      "estimatedEpsAvg": 0.31,
      "estimatedEpsHigh": 0.37,
      "estimatedEpsLow": 0.25,
      "numberAnalystEstimatedRevenue": 16,
      "numberAnalystsEstimatedEps": 16
    },
    {
      "symbol": "CRM",
      "date": "2013-01-31",
      "estimatedRevenueLow": 2178756363,
      "estimatedRevenueHigh": 3268134544,
      "estimatedRevenueAvg": 2723445454,
      "estimatedEbitdaLow": 92378800,
      "estimatedEbitdaHigh": 138568200,
      "estimatedEbitdaAvg": 115473500,
      "estimatedEbitLow": -113154840,
      "estimatedEbitHigh": -75436560,
      "estimatedEbitAvg": -94295700,
      "estimatedNetIncomeLow": -302745960,
      "estimatedNetIncomeHigh": -201830640,
      "estimatedNetIncomeAvg": -252288300,
      "estimatedSgaExpenseLow": 1462225040,
      "estimatedSgaExpenseHigh": 2193337560,
      "estimatedSgaExpenseAvg": 1827781300,
      "estimatedEpsAvg": 0.35,
      "estimatedEpsHigh": 0.43,
      "estimatedEpsLow": 0.27,
      "numberAnalystEstimatedRevenue": 20,
      "numberAnalystsEstimatedEps": 20
    },
    {
      "symbol": "CRM",
      "date": "2012-01-31",
      "estimatedRevenueLow": 1475362222,
      "estimatedRevenueHigh": 2213043333,
      "estimatedRevenueAvg": 1844202778,
      "estimatedEbitdaLow": 87686390,
      "estimatedEbitdaHigh": 131529584,
      "estimatedEbitdaAvg": 109607987,
      "estimatedEbitLow": -30539191,
      "estimatedEbitHigh": -20359461,
      "estimatedEbitAvg": -25449326,
      "estimatedNetIncomeLow": -2089476,
      "estimatedNetIncomeHigh": 3810570,
      "estimatedNetIncomeAvg": 860548,
      "estimatedSgaExpenseLow": 959828690,
      "estimatedSgaExpenseHigh": 1439743034,
      "estimatedSgaExpenseAvg": 1199785862,
      "estimatedEpsAvg": 0.24,
      "estimatedEpsHigh": 0.28,
      "estimatedEpsLow": 0.2,
      "numberAnalystEstimatedRevenue": 17,
      "numberAnalystsEstimatedEps": 17
    },
    {
      "symbol": "CRM",
      "date": "2011-01-31",
      "estimatedRevenueLow": 1222960000,
      "estimatedRevenueHigh": 1834440000,
      "estimatedRevenueAvg": 1528700000,
      "estimatedEbitdaLow": 172979200,
      "estimatedEbitdaHigh": 259468800,
      "estimatedEbitdaAvg": 216224000,
      "estimatedEbitLow": 98725600,
      "estimatedEbitHigh": 148088400,
      "estimatedEbitAvg": 123407000,
      "estimatedNetIncomeLow": 59164000,
      "estimatedNetIncomeHigh": 88746000,
      "estimatedNetIncomeAvg": 73955000,
      "estimatedSgaExpenseLow": 771639200,
      "estimatedSgaExpenseHigh": 1157458800,
      "estimatedSgaExpenseAvg": 964549000,
      "estimatedEpsAvg": 0.27,
      "estimatedEpsHigh": 0.33,
      "estimatedEpsLow": 0.21,
      "numberAnalystEstimatedRevenue": 19,
      "numberAnalystsEstimatedEps": 19
    },
    {
      "symbol": "CRM",
      "date": "2010-01-31",
      "estimatedRevenueLow": 854673333,
      "estimatedRevenueHigh": 1282010000,
      "estimatedRevenueAvg": 1068341667,
      "estimatedEbitdaLow": 124184053,
      "estimatedEbitdaHigh": 186276079,
      "estimatedEbitdaAvg": 155230066,
      "estimatedEbitLow": 70849199,
      "estimatedEbitHigh": 106273799,
      "estimatedEbitAvg": 88561499,
      "estimatedNetIncomeLow": 49395053,
      "estimatedNetIncomeHigh": 74092579,
      "estimatedNetIncomeAvg": 61743816,
      "estimatedSgaExpenseLow": 494325693,
      "estimatedSgaExpenseHigh": 741488538,
      "estimatedSgaExpenseAvg": 617907116,
      "estimatedEpsAvg": 0.11,
      "estimatedEpsHigh": 0.13,
      "estimatedEpsLow": 0.09,
      "numberAnalystEstimatedRevenue": 12,
      "numberAnalystsEstimatedEps": 12
    },
    {
      "symbol": "CRM",
      "date": "2009-01-31",
      "estimatedRevenueLow": 716520000,
      "estimatedRevenueHigh": 1074780000,
      "estimatedRevenueAvg": 895650000,
      "estimatedEbitdaLow": 132721680,
      "estimatedEbitdaHigh": 199082520,
      "estimatedEbitdaAvg": 165902100,
      "estimatedEbitLow": 47564000,
      "estimatedEbitHigh": 71346000,
      "estimatedEbitAvg": 59455000,
      "estimatedNetIncomeLow": 30233520,
      "estimatedNetIncomeHigh": 45350280,
      "estimatedNetIncomeAvg": 37791900,
      "estimatedSgaExpenseLow": 530914560,
      "estimatedSgaExpenseHigh": 796371840,
      "estimatedSgaExpenseAvg": 663643200,
      "estimatedEpsAvg": 0.07,
      "estimatedEpsHigh": 0.07128347,
      "estimatedEpsLow": 0.06919233,
      "numberAnalystEstimatedRevenue": 10,
      "numberAnalystsEstimatedEps": 10
    },
    {
      "symbol": "CRM",
      "date": "2007-01-31",
      "estimatedRevenueLow": 255920000,
      "estimatedRevenueHigh": 383880000,
      "estimatedRevenueAvg": 319900000,
      "estimatedEbitdaLow": 38625200,
      "estimatedEbitdaHigh": 57937800,
      "estimatedEbitdaAvg": 48281500,
      "estimatedEbitLow": 2206960,
      "estimatedEbitHigh": 4972640,
      "estimatedEbitAvg": 3589800,
      "estimatedNetIncomeLow": 4597720,
      "estimatedNetIncomeHigh": 7285080,
      "estimatedNetIncomeAvg": 5941400,
      "estimatedSgaExpenseLow": 250023440,
      "estimatedSgaExpenseHigh": 375035160,
      "estimatedSgaExpenseAvg": 312529300,
      "estimatedEpsAvg": 0.04,
      "estimatedEpsHigh": 0.04073341,
      "estimatedEpsLow": 0.03953848,
      "numberAnalystEstimatedRevenue": 8,
      "numberAnalystsEstimatedEps": 8
    }
  ]
}