{
  "ticker": "GOOGL",
  "endpoint": "analyst-estimates-annual",
  "fetched_at": "2025-09-05T14:21:36.437979",
  "data": [
    {
      "symbol": "GOOGL",
      "date": "2029-12-31",
      "estimatedRevenueLow": 576019640716,
      "estimatedRevenueHigh": 618364561143,
      "estimatedRevenueAvg": 592830657143,
      "estimatedEbitdaLow": 201335246070,
      "estimatedEbitdaHigh": 216136000023,
      "estimatedEbitdaAvg": 207211174406,
      "estimatedEbitLow": 172122074063,
      "estimatedEbitHigh": 184775280681,
      "estimatedEbitAvg": 177145421897,
      "estimatedNetIncomeLow": 193454385765,
      "estimatedNetIncomeHigh": 212105592917,
      "estimatedNetIncomeAvg": 200858981596,
      "estimatedSgaExpenseLow": 82255334932,
      "estimatedSgaExpenseHigh": 88302169738,
      "estimatedSgaExpenseAvg": 84655940205,
      "estimatedEpsAvg": 16.13714,
      "estimatedEpsHigh": 17.0407,
      "estimatedEpsLow": 15.54225,
      "numberAnalystEstimatedRevenue": 18,
      "numberAnalystsEstimatedEps": 16
    },
    {
      "symbol": "GOOGL",
      "date": "2028-12-31",
      "estimatedRevenueLow": 527121570006,
      "estimatedRevenueHigh": 565871847531,
      "estimatedRevenueAvg": 542505506154,
      "estimatedEbitdaLow": 184243979726,
      "estimatedEbitdaHigh": 197788303755,
      "estimatedEbitdaAvg": 189621102920,
      "estimatedEbitLow": 157510701892,
      "estimatedEbitHigh": 169089782998,
      "estimatedEbitAvg": 162107619792,
      "estimatedNetIncomeLow": 165953859493,
      "estimatedNetIncomeHigh": 181953606704,
      "estimatedNetIncomeAvg": 172305812533,
      "estimatedSgaExpenseLow": 75272713335,
      "estimatedSgaExpenseHigh": 80806234818,
      "estimatedSgaExpenseAvg": 77469532212,
      "estimatedEpsAvg": 13.84316,
      "estimatedEpsHigh": 14.61827,
      "estimatedEpsLow": 13.33284,
      "numberAnalystEstimatedRevenue": 18,
      "numberAnalystsEstimatedEps": 26
    },
    {
      "symbol": "GOOGL",
      "date": "2027-12-31",
      "estimatedRevenueLow": 487330554994,
      "estimatedRevenueHigh": 489408362963,
      "estimatedRevenueAvg": 488369458979,
      "estimatedEbitdaLow": 170335888348,
      "estimatedEbitdaHigh": 171062141325,
      "estimatedEbitdaAvg": 170699014837,
      "estimatedEbitLow": 145620635046,
      "estimatedEbitHigh": 146241510780,
      "estimatedEbitAvg": 145931072913,
      "estimatedNetIncomeLow": 136183622770,
      "estimatedNetIncomeHigh": 165564019453,
      "estimatedNetIncomeAvg": 139721970770,
      "estimatedSgaExpenseLow": 69590575026,
      "estimatedSgaExpenseHigh": 69887285031,
      "estimatedSgaExpenseAvg": 69738930028,
      "estimatedEpsAvg": 12.1164,
      "estimatedEpsHigh": 13.30152,
      "estimatedEpsLow": 10.94108,
      "numberAnalystEstimatedRevenue": 36,
      "numberAnalystsEstimatedEps": 35
    },
    {
      "symbol": "GOOGL",
      "date": "2026-12-31",
      "estimatedRevenueLow": 420837980320,
      "estimatedRevenueHigh": 454894300921,
      "estimatedRevenueAvg": 440595576864,
      "estimatedEbitdaLow": 147094842492,
      "estimatedEbitdaHigh": 158998495083,
      "estimatedEbitdaAvg": 154000684378,
      "estimatedEbitLow": 125751798892,
      "estimatedEbitHigh": 135928265322,
      "estimatedEbitAvg": 131655622747,
      "estimatedNetIncomeLow": 126870777370,
      "estimatedNetIncomeHigh": 137995408091,
      "estimatedNetIncomeAvg": 132433092730.5,
      "estimatedSgaExpenseLow": 60095466502,
      "estimatedSgaExpenseHigh": 64958693135,
      "estimatedSgaExpenseAvg": 62916842036,
      "estimatedEpsAvg": 10.64478,
      "estimatedEpsHigh": 11.08664,
      "estimatedEpsLow": 10.19288,
      "numberAnalystEstimatedRevenue": 42,
      "numberAnalystsEstimatedEps": 46
    },
    {
      "symbol": "GOOGL",
      "date": "2025-12-31",
      "estimatedRevenueLow": 387340537493,
      "estimatedRevenueHigh": 399065618781,
      "estimatedRevenueAvg": 394712947760,
      "estimatedEbitdaLow": 135386533577,
      "estimatedEbitdaHigh": 139484782942,
      "estimatedEbitdaAvg": 137963400633,
      "estimatedEbitLow": 115742332326,
      "estimatedEbitHigh": 119245937355,
      "estimatedEbitAvg": 117945303295,
      "estimatedNetIncomeLow": 118228202919,
      "estimatedNetIncomeHigh": 126637769530,
      "estimatedNetIncomeAvg": 120855014970,
      "estimatedSgaExpenseLow": 55312047354,
      "estimatedSgaExpenseHigh": 56986383471,
      "estimatedSgaExpenseAvg": 56364824087,
      "estimatedEpsAvg": 9.9357,
      "estimatedEpsHigh": 10.17416,
      "estimatedEpsLow": 9.49853,
      "numberAnalystEstimatedRevenue": 42,
      "numberAnalystsEstimatedEps": 46
    },
    {
      "symbol": "GOOGL",
      "date": "2024-12-31",
      "estimatedRevenueLow": 348444826629,
      "estimatedRevenueHigh": 352653556963,
      "estimatedRevenueAvg": 350477857384,
      "estimatedEbitdaLow": 121791376461,
      "estimatedEbitdaHigh": 123262447406,
      "estimatedEbitdaAvg": 122501978528,
      "estimatedEbitLow": 104119793869,
      "estimatedEbitHigh": 105377416601,
      "estimatedEbitAvg": 104727289596,
      "estimatedNetIncomeLow": 97933991767,
      "estimatedNetIncomeHigh": 103409302598,
      "estimatedNetIncomeAvg": 100671647182.5,
      "estimatedSgaExpenseLow": 49757758058,
      "estimatedSgaExpenseHigh": 50358762779,
      "estimatedSgaExpenseAvg": 50048073898,
      "estimatedEpsAvg": 8.01804,
      "estimatedEpsHigh": 8.30797,
      "estimatedEpsLow": 7.86808,
      "numberAnalystEstimatedRevenue": 33,
      "numberAnalystsEstimatedEps": 38
    },
    {
      "symbol": "GOOGL",
      "date": "2023-12-31",
      "estimatedRevenueLow": 304903702067,
      "estimatedRevenueHigh": 307642573868,
      "estimatedRevenueAvg": 306237100181,
      "estimatedEbitdaLow": 86226072190,
      "estimatedEbitdaHigh": 129339108285,
      "estimatedEbitdaAvg": 107782590238,
      "estimatedEbitLow": 71293748403,
      "estimatedEbitHigh": 106940622607,
      "estimatedEbitAvg": 89117185505,
      "estimatedNetIncomeLow": 70125599999,
      "estimatedNetIncomeHigh": 105188400000,
      "estimatedNetIncomeAvg": 87657000000,
      "estimatedSgaExpenseLow": 34731114799,
      "estimatedSgaExpenseHigh": 52096672201,
      "estimatedSgaExpenseAvg": 43413893500,
      "estimatedEpsAvg": 5.74475,
      "estimatedEpsHigh": 5.88414,
      "estimatedEpsLow": 5.57549,
      "numberAnalystEstimatedRevenue": 29,
      "numberAnalystsEstimatedEps": 32
    },
    {
      "symbol": "GOOGL",
      "date": "2022-12-31",
      "estimatedRevenueLow": 278552166517,
      "estimatedRevenueHigh": 285920346254,
      "estimatedRevenueAvg": 282140117275,
      "estimatedEbitdaLow": 78387338355,
      "estimatedEbitdaHigh": 117581007534,
      "estimatedEbitdaAvg": 97984172945,
      "estimatedEbitLow": 64812498549,
      "estimatedEbitHigh": 97218747826,
      "estimatedEbitAvg": 81015623188,
      "estimatedNetIncomeLow": 56411506308,
      "estimatedNetIncomeHigh": 84617259463,
      "estimatedNetIncomeAvg": 70514382886,
      "estimatedSgaExpenseLow": 31573740728,
      "estimatedSgaExpenseHigh": 47360611093,
      "estimatedSgaExpenseAvg": 39467175911,
      "estimatedEpsAvg": 4.71713,
      "estimatedEpsHigh": 4.79929,
      "estimatedEpsLow": 4.63915,
      "numberAnalystEstimatedRevenue": 29,
      "numberAnalystsEstimatedEps": 19
    },
    {
      "symbol": "GOOGL",
      "date": "2021-12-31",
      "estimatedRevenueLow": 249147657584,
      "estimatedRevenueHigh": 258257944798,
      "estimatedRevenueAvg": 253189995257,
      "estimatedEbitdaLow": 64461779570,
      "estimatedEbitdaHigh": 96692669355,
      "estimatedEbitdaAvg": 80577224463,
      "estimatedEbitLow": 48990664306,
      "estimatedEbitHigh": 73485996460,
      "estimatedEbitAvg": 61238330383,
      "estimatedNetIncomeLow": 47335069755,
      "estimatedNetIncomeHigh": 71002604636,
      "estimatedNetIncomeAvg": 59168837196,
      "estimatedSgaExpenseLow": 22821906759,
      "estimatedSgaExpenseHigh": 34232860140,
      "estimatedSgaExpenseAvg": 28527383450,
      "estimatedEpsAvg": 5.42868,
      "estimatedEpsHigh": 5.56994,
      "estimatedEpsLow": 5.31601,
      "numberAnalystEstimatedRevenue": 18,
      "numberAnalystsEstimatedEps": 25
    },
    {
      "symbol": "GOOGL",
      "date": "2020-12-31",
      "estimatedRevenueLow": 174947208573,
      "estimatedRevenueHigh": 181344295878,
      "estimatedRevenueAvg": 177785668701,
      "estimatedEbitdaLow": 36199309683,
      "estimatedEbitdaHigh": 54298964526,
      "estimatedEbitdaAvg": 45249137105,
      "estimatedEbitLow": 24208375544,
      "estimatedEbitHigh": 36312563316,
      "estimatedEbitAvg": 30260469430,
      "estimatedNetIncomeLow": 23401409380,
      "estimatedNetIncomeHigh": 35102114072,
      "estimatedNetIncomeAvg": 29251761726,
      "estimatedSgaExpenseLow": 17790419858,
      "estimatedSgaExpenseHigh": 26685629787,
      "estimatedSgaExpenseAvg": 22238024823,
      "estimatedEpsAvg": 2.6168,
      "estimatedEpsHigh": 2.68489,
      "estimatedEpsLow": 2.56249,
      "numberAnalystEstimatedRevenue": 18,
      "numberAnalystsEstimatedEps": 18
    },
    {
      "symbol": "GOOGL",
      "date": "2019-12-31",
      "estimatedRevenueLow": 160126942505,
      "estimatedRevenueHigh": 165982114699,
      "estimatedRevenueAvg": 162724948757,
      "estimatedEbitdaLow": 38185917614,
      "estimatedEbitdaHigh": 57278876422,
      "estimatedEbitdaAvg": 47732397018,
      "estimatedEbitLow": 25737843472,
      "estimatedEbitHigh": 38606765210,
      "estimatedEbitAvg": 32172304341,
      "estimatedNetIncomeLow": 25108117211,
      "estimatedNetIncomeHigh": 37662175817,
      "estimatedNetIncomeAvg": 31385146514,
      "estimatedSgaExpenseLow": 21149137629,
      "estimatedSgaExpenseHigh": 31723706445,
      "estimatedSgaExpenseAvg": 26436422037,
      "estimatedEpsAvg": 2.32097,
      "estimatedEpsHigh": 2.38136,
      "estimatedEpsLow": 2.2728,
      "numberAnalystEstimatedRevenue": 17,
      "numberAnalystsEstimatedEps": 33
    },
    {
      "symbol": "GOOGL",
      "date": "2018-12-31",
      "estimatedRevenueLow": 134270205134,
      "estimatedRevenueHigh": 139179904647,
      "estimatedRevenueAvg": 136448694444,
      "estimatedEbitdaLow": 28977367529,
      "estimatedEbitdaHigh": 43466051293,
      "estimatedEbitdaAvg": 36221709411,
      "estimatedEbitLow": 16900815982,
      "estimatedEbitHigh": 25351223972,
      "estimatedEbitAvg": 21126019978,
      "estimatedNetIncomeLow": 19532977824,
      "estimatedNetIncomeHigh": 29299466738,
      "estimatedNetIncomeAvg": 24416222281,
      "estimatedSgaExpenseLow": 17356320960,
      "estimatedSgaExpenseHigh": 26034481441,
      "estimatedSgaExpenseAvg": 21695401201,
      "estimatedEpsAvg": 2.08117,
      "estimatedEpsHigh": 2.13532,
      "estimatedEpsLow": 2.03797,
      "numberAnalystEstimatedRevenue": 8,
      "numberAnalystsEstimatedEps": 7
    },
    {
      "symbol": "GOOGL",
      "date": "2017-12-31",
      "estimatedRevenueLow": 87463100955,
      "estimatedRevenueHigh": 90661260544,
      "estimatedRevenueAvg": 88882160606,
      "estimatedEbitdaLow": 17491760180,
      "estimatedEbitdaHigh": 26237640271,
      "estimatedEbitdaAvg": 21864700226,
      "estimatedEbitLow": 19537501417,
      "estimatedEbitHigh": 29306252125,
      "estimatedEbitAvg": 24421876771,
      "estimatedNetIncomeLow": 7492014868,
      "estimatedNetIncomeHigh": 14342751763,
      "estimatedNetIncomeAvg": 10917383316,
      "estimatedSgaExpenseLow": 14806871777,
      "estimatedSgaExpenseHigh": 22210307665,
      "estimatedSgaExpenseAvg": 18508589721,
      "estimatedEpsAvg": 1.61386,
      "estimatedEpsHigh": 1.65585,
      "estimatedEpsLow": 1.58036,
      "numberAnalystEstimatedRevenue": 16,
      "numberAnalystsEstimatedEps": 15
    },
    {
      "symbol": "GOOGL",
      "date": "2016-12-31",
      "estimatedRevenueLow": 71725532703,
      "estimatedRevenueHigh": 74348235279,
      "estimatedRevenueAvg": 72889255556,
      "estimatedEbitdaLow": 24254021846,
      "estimatedEbitdaHigh": 36381032769,
      "estimatedEbitdaAvg": 30317527308,
      "estimatedEbitLow": 18928896440,
      "estimatedEbitHigh": 28393344661,
      "estimatedEbitAvg": 23661120551,
      "estimatedNetIncomeLow": 15522946080,
      "estimatedNetIncomeHigh": 23284419122,
      "estimatedNetIncomeAvg": 19403682601,
      "estimatedSgaExpenseLow": 13955942982,
      "estimatedSgaExpenseHigh": 20933914474,
      "estimatedSgaExpenseAvg": 17444928728,
      "estimatedEpsAvg": 1.72364,
      "estimatedEpsHigh": 1.76849,
      "estimatedEpsLow": 1.68787,
      "numberAnalystEstimatedRevenue": 11,
      "numberAnalystsEstimatedEps": 12
    },
    {
      "symbol": "GOOGL",
      "date": "2015-12-31",
      "estimatedRevenueLow": 59311554799,
      "estimatedRevenueHigh": 61480330153,
      "estimatedRevenueAvg": 60273865000,
      "estimatedEbitdaLow": 19198264630,
      "estimatedEbitdaHigh": 28797396948,
      "estimatedEbitdaAvg": 23997830789,
      "estimatedEbitLow": 14966768712,
      "estimatedEbitHigh": 22450153068,
      "estimatedEbitAvg": 18708460890,
      "estimatedNetIncomeLow": 12621305194,
      "estimatedNetIncomeHigh": 18931957791,
      "estimatedNetIncomeAvg": 15776631493,
      "estimatedSgaExpenseLow": 14996937776,
      "estimatedSgaExpenseHigh": 22495406665,
      "estimatedSgaExpenseAvg": 18746172221,
      "estimatedEpsAvg": 1.44981,
      "estimatedEpsHigh": 1.48754,
      "estimatedEpsLow": 1.41972,
      "numberAnalystEstimatedRevenue": 8,
      "numberAnalystsEstimatedEps": 7
    },
    {
      "symbol": "GOOGL",
      "date": "2014-12-31",
      "estimatedRevenueLow": 54230365700,
      "estimatedRevenueHigh": 81345548552,
      "estimatedRevenueAvg": 67787957126,
      "estimatedEbitdaLow": 18780939496,
      "estimatedEbitdaHigh": 28171409246,
      "estimatedEbitdaAvg": 23476174371,
      "estimatedEbitLow": 13552007555,
      "estimatedEbitHigh": 20328011335,
      "estimatedEbitAvg": 16940009445,
      "estimatedNetIncomeLow": 11617824069,
      "estimatedNetIncomeHigh": 17426736105,
      "estimatedNetIncomeAvg": 14522280087,
      "estimatedSgaExpenseLow": 11489239912,
      "estimatedSgaExpenseHigh": 17233859867,
      "estimatedSgaExpenseAvg": 14361549890,
      "estimatedEpsAvg": 1.345,
      "estimatedEpsHigh": 1.61,
      "estimatedEpsLow": 1.08,
      "numberAnalystEstimatedRevenue": 17,
      "numberAnalystsEstimatedEps": 17
    },
    {
      "symbol": "GOOGL",
      "date": "2013-12-31",
      "estimatedRevenueLow": 44467442531,
      "estimatedRevenueHigh": 66701163797,
      "estimatedRevenueAvg": 55584303164,
      "estimatedEbitdaLow": 15665803940,
      "estimatedEbitdaHigh": 23498705910,
      "estimatedEbitdaAvg": 19582254925,
      "estimatedEbitLow": 11155195557,
      "estimatedEbitHigh": 16732793336,
      "estimatedEbitAvg": 13943994447,
      "estimatedNetIncomeLow": 10193364145,
      "estimatedNetIncomeHigh": 15290046219,
      "estimatedNetIncomeAvg": 12741705182,
      "estimatedSgaExpenseLow": 10316882529,
      "estimatedSgaExpenseHigh": 15475323793,
      "estimatedSgaExpenseAvg": 12896103162,
      "estimatedEpsAvg": 1.1,
      "estimatedEpsHigh": 1.32,
      "estimatedEpsLow": 0.88,
      "numberAnalystEstimatedRevenue": 19,
      "numberAnalystsEstimatedEps": 19
    },
    {
      "symbol": "GOOGL",
      "date": "2012-12-31",
      "estimatedRevenueLow": 41132626276,
      "estimatedRevenueHigh": 61698939414,
      "estimatedRevenueAvg": 51415782845,
      "estimatedEbitdaLow": 13326438074,
      "estimatedEbitdaHigh": 19989657114,
      "estimatedEbitdaAvg": 16658047594,
      "estimatedEbitLow": 10359013879,
      "estimatedEbitHigh": 15538520818,
      "estimatedEbitAvg": 12948767349,
      "estimatedNetIncomeLow": 8699257353,
      "estimatedNetIncomeHigh": 13048886031,
      "estimatedNetIncomeAvg": 10874071692,
      "estimatedSgaExpenseLow": 8229594382,
      "estimatedSgaExpenseHigh": 12344391573,
      "estimatedSgaExpenseAvg": 10286992978,
      "estimatedEpsAvg": 1.045,
      "estimatedEpsHigh": 1.26,
      "estimatedEpsLow": 0.83,
      "numberAnalystEstimatedRevenue": 9,
      "numberAnalystsEstimatedEps": 9
    },
    {
      "symbol": "GOOGL",
      "date": "2011-12-31",
      "estimatedRevenueLow": 29466994179,
      "estimatedRevenueHigh": 44200491269,
      "estimatedRevenueAvg": 36833742724,
      "estimatedEbitdaLow": 11021106675,
      "estimatedEbitdaHigh": 16531660011,
      "estimatedEbitdaAvg": 13776383344,
      "estimatedEbitLow": 9132981244,
      "estimatedEbitHigh": 13699471866,
      "estimatedEbitAvg": 11416226555,
      "estimatedNetIncomeLow": 7530082259,
      "estimatedNetIncomeHigh": 11295123390,
      "estimatedNetIncomeAvg": 9412602825,
      "estimatedSgaExpenseLow": 6086678472,
      "estimatedSgaExpenseHigh": 9130017708,
      "estimatedSgaExpenseAvg": 7608348090,
      "estimatedEpsAvg": 0.86,
      "estimatedEpsHigh": 1.03,
      "estimatedEpsLow": 0.69,
      "numberAnalystEstimatedRevenue": 15,
      "numberAnalystsEstimatedEps": 15
    },
    {
      "symbol": "GOOGL",
      "date": "2010-12-31",
      "estimatedRevenueLow": 22007679743,
      "estimatedRevenueHigh": 33011519616,
      "estimatedRevenueAvg": 27509599680,
      "estimatedEbitdaLow": 9146367002,
      "estimatedEbitdaHigh": 13719550505,
      "estimatedEbitdaAvg": 11432958754,
      "estimatedEbitLow": 7794504458,
      "estimatedEbitHigh": 11691756689,
      "estimatedEbitAvg": 9743130574,
      "estimatedNetIncomeLow": 6370643441,
      "estimatedNetIncomeHigh": 9555965162,
      "estimatedNetIncomeAvg": 7963304302,
      "estimatedSgaExpenseLow": 3567964450,
      "estimatedSgaExpenseHigh": 5351946676,
      "estimatedSgaExpenseAvg": 4459955563,
      "estimatedEpsAvg": 0.655,
      "estimatedEpsHigh": 0.78,
      "estimatedEpsLow": 0.53,
      "numberAnalystEstimatedRevenue": 17,
      "numberAnalystsEstimatedEps": 17
    },
    {
      "symbol": "GOOGL",
      "date": "2009-12-31",
      "estimatedRevenueLow": 17777421004,
      "estimatedRevenueHigh": 26666131507,
      "estimatedRevenueAvg": 22221776256,
      "estimatedEbitdaLow": 7448649285,
      "estimatedEbitdaHigh": 11172973929,
      "estimatedEbitdaAvg": 9310811607,
      "estimatedEbitLow": 6248680024,
      "estimatedEbitHigh": 9373020039,
      "estimatedEbitAvg": 7810850032,
      "estimatedNetIncomeLow": 4901681757,
      "estimatedNetIncomeHigh": 7352522638,
      "estimatedNetIncomeAvg": 6127102198,
      "estimatedSgaExpenseLow": 2744806910,
      "estimatedSgaExpenseHigh": 4117210365,
      "estimatedSgaExpenseAvg": 3431008638,
      "estimatedEpsAvg": 0.51,
      "estimatedEpsHigh": 0.61,
      "estimatedEpsLow": 0.41,
      "numberAnalystEstimatedRevenue": 12,
      "numberAnalystsEstimatedEps": 12
    },
    {
      "symbol": "GOOGL",
      "date": "2008-12-31",
      "estimatedRevenueLow": 16935795486,
      "estimatedRevenueHigh": 25403693230,
      "estimatedRevenueAvg": 21169744358,
      "estimatedEbitdaLow": 5709924625,
      "estimatedEbitdaHigh": 8564886939,
      "estimatedEbitdaAvg": 7137405783,
      "estimatedEbitLow": 5152576710,
      "estimatedEbitHigh": 7728865067,
      "estimatedEbitAvg": 6440720889,
      "estimatedNetIncomeLow": 3280005953,
      "estimatedNetIncomeHigh": 4920008930,
      "estimatedNetIncomeAvg": 4100007442,
      "estimatedSgaExpenseLow": 2915388561,
      "estimatedSgaExpenseHigh": 4373082844,
      "estimatedSgaExpenseAvg": 3644235703,
      "estimatedEpsAvg": 0.465,
      "estimatedEpsHigh": 0.56,
      "estimatedEpsLow": 0.37,
      "numberAnalystEstimatedRevenue": 15,
      "numberAnalystsEstimatedEps": 15
    },
    {
      "symbol": "GOOGL",
      "date": "2007-12-31",
      "estimatedRevenueLow": 12846722691,
      "estimatedRevenueHigh": 19270084038,
      "estimatedRevenueAvg": 16058403365,
      "estimatedEbitdaLow": 5132835931,
      "estimatedEbitdaHigh": 7699253897,
      "estimatedEbitdaAvg": 6416044914,
      "estimatedEbitLow": 3925792375,
      "estimatedEbitHigh": 5888688564,
      "estimatedEbitAvg": 4907240470,
      "estimatedNetIncomeLow": 3246613063,
      "estimatedNetIncomeHigh": 4869919595,
      "estimatedNetIncomeAvg": 4058266329,
      "estimatedSgaExpenseLow": 2125617379,
      "estimatedSgaExpenseHigh": 3188426069,
      "estimatedSgaExpenseAvg": 2657021724,
      "estimatedEpsAvg": 0.365,
      "estimatedEpsHigh": 0.44,
      "estimatedEpsLow": 0.29,
      "numberAnalystEstimatedRevenue": 15,
      "numberAnalystsEstimatedEps": 15
    },
    {
      "symbol": "GOOGL",
      "date": "2006-12-31",
      "estimatedRevenueLow": 7538608512,
      "estimatedRevenueHigh": 11307912768,
      "estimatedRevenueAvg": 9423260641,
      "estimatedEbitdaLow": 3259059033,
      "estimatedEbitdaHigh": 4888588550,
      "estimatedEbitdaAvg": 4073823792,
      "estimatedEbitLow": 2524574534,
      "estimatedEbitHigh": 3786861803,
      "estimatedEbitAvg": 3155718169,
      "estimatedNetIncomeLow": 2190405129,
      "estimatedNetIncomeHigh": 3285607694,
      "estimatedNetIncomeAvg": 2738006412,
      "estimatedSgaExpenseLow": 1136146479,
      "estimatedSgaExpenseHigh": 1704219721,
      "estimatedSgaExpenseAvg": 1420183100,
      "estimatedEpsAvg": 0.21,
      "estimatedEpsHigh": 0.26,
      "estimatedEpsLow": 0.16,
      "numberAnalystEstimatedRevenue": 19,
      "numberAnalystsEstimatedEps": 19
    },
    {
      "symbol": "GOOGL",
      "date": "2005-12-31",
      "estimatedRevenueLow": 4795028351,
      "estimatedRevenueHigh": 7192542528,
      "estimatedRevenueAvg": 5993785440,
      "estimatedEbitdaLow": 1766333438,
      "estimatedEbitdaHigh": 2649500156,
      "estimatedEbitdaAvg": 2207916797,
      "estimatedEbitLow": 1451795663,
      "estimatedEbitHigh": 2177693495,
      "estimatedEbitAvg": 1814744579,
      "estimatedNetIncomeLow": 1037249172,
      "estimatedNetIncomeHigh": 1555873759,
      "estimatedNetIncomeAvg": 1296561466,
      "estimatedSgaExpenseLow": 715208252,
      "estimatedSgaExpenseHigh": 1072812378,
      "estimatedSgaExpenseAvg": 894010315,
      "estimatedEpsAvg": 0.12,
      "estimatedEpsHigh": 0.15,
      "estimatedEpsLow": 0.09,
      "numberAnalystEstimatedRevenue": 19,
      "numberAnalystsEstimatedEps": 19
    }
  ]
}